{
  "plotStartTime": 1570329196100,
  "plotEndTime": 1570331391263,
  "simulationsProcessed": 100000,
  "dataFile": {
    "path": "/home/scec-02/kmilner/ucerf3/etas_sim/2019_08_09-ComCatM7p1_ci38457511_ShakeMapSurfaces_NoERT-noSpont-no_ert/results_complete.bin"
  },
  "launcherGitHash": "ca84ae8f80d4b448a3e31e6f911c599174c160e3",
  "launcherGitTime": 1570130648000,
  "plots": [
    {
      "className": "scratch.UCERF3.erf.ETAS.analysis.ETAS_MFD_Plot",
      "version": 2,
      "time": 1567178407449,
      "markdown": [
        "## Probabilities Summary Table",
        "*[(top)](#table-of-contents)*",
        "",
        "| Magnitude | 1 Hour Prob | 1 Day Prob | 1 Week Prob | 1 Month Prob | 1 Year Prob | 10 Year Prob |",
        "|-----|-----|-----|-----|-----|-----|-----|",
        "| **M\u0026ge;4** | 1.000 (100.00%) | 1.000 (100.00%) | 1.000 (100.00%) | 1.000 (100.00%) | 1.000 (100.00%) | 1.000 (100.00%) |",
        "| **M\u0026ge;4.5** | 0.991 (99.12%) | 1.000 (100.00%) | 1.000 (100.00%) | 1.000 (100.00%) | 1.000 (100.00%) | 1.000 (100.00%) |",
        "| **M\u0026ge;5** | 0.775 (77.52%) | 0.978 (97.78%) | 0.996 (99.58%) | 0.999 (99.87%) | 1.000 (99.98%) | 1.000 (100.00%) |",
        "| **M\u0026ge;5.5** | 0.361 (36.15%) | 0.690 (68.99%) | 0.815 (81.49%) | 0.877 (87.67%) | 0.939 (93.95%) | 0.968 (96.79%) |",
        "| **M\u0026ge;6** | 0.111 (11.11%) | 0.272 (27.22%) | 0.376 (37.64%) | 0.449 (44.87%) | 0.560 (56.03%) | 0.644 (64.44%) |",
        "| **M\u0026ge;6.5** | 0.025 (2.53%) | 0.070 (7.01%) | 0.106 (10.60%) | 0.135 (13.47%) | 0.188 (18.77%) | 0.237 (23.73%) |",
        "| **M\u0026ge;7** | 9.53E-3 (0.95%) | 0.027 (2.73%) | 0.041 (4.12%) | 0.053 (5.30%) | 0.076 (7.61%) | 0.100 (9.98%) |",
        "| **M\u0026ge;7.1** | 7.97E-3 (0.80%) | 0.023 (2.30%) | 0.035 (3.48%) | 0.045 (4.53%) | 0.065 (6.53%) | 0.086 (8.63%) |",
        "| **M\u0026ge;7.5** | 2.94E-3 (0.29%) | 9.26E-3 (0.93%) | 0.014 (1.42%) | 0.019 (1.85%) | 0.027 (2.74%) | 0.038 (3.79%) |",
        "| **M\u0026ge;8** | 4.00E-5 (0.00%) | 1.60E-4 (0.02%) | 2.90E-4 (0.03%) | 4.00E-4 (0.04%) | 7.00E-4 (0.07%) | 1.00E-3 (0.10%) |",
        "",
        "## Magnitude Number Distribution",
        "*[(top)](#table-of-contents)*",
        "",
        "### 10 Year Magnitude Number Distribution",
        "*[(top)](#table-of-contents)*",
        "",
        "**Legend**",
        "* **Mean** (thick black line): mean expected number across all 100000 catalogs",
        "* **2.5%,97.5%** (thin black lines): expected number percentiles across all 100000 catalogs",
        "* **Median** (thin blue line): median expected number across all 100000 catalogs",
        "* **Mode** (thin cyan line): modal expected number across all 100000 catalogs",
        "* **10 yr Probability** (thin red line): 10 year probability calculated as the fraction of catalogs with at least 1 occurrence",
        "* **10 yr Supraseismogenic Probability** (thin dashed red line): same as above, but only for supraseismogenic ruptures on explicitly modeled UCERF3 faults",
        "* **95% Conf** (light red shaded region): binomial 95% confidence bounds on probability",
        "* **Primary** (thin green line): mean expected number from primary triggered aftershocks only (no secondary, tertiary, etc...) across all 100000 catalogs",
        "",
        "![MFD Plot](plots/10yr_mag_num_cumulative_triggered.png)",
        "",
        "| Mag | Mean | 2.5 %ile | 97.5 %ile | Median | Mode | 10 yr Probability | 10 yr Supra-Seis Prob | Primary Aftershocks Mean |",
        "|-----|-----|-----|-----|-----|-----|-----|-----|-----|",
        "| **M\u0026ge;2.5** | 5914.612 | 3650.000 | 18657.000 | 4625.000 | 4124.000 | 1.000 (100.00%) | 0.347 (34.72%) | 2385.233 |",
        "| **M\u0026ge;2.6** | 4697.941 | 2893.000 | 14832.000 | 3675.000 | 3356.000 | 1.000 (100.00%) | 0.347 (34.72%) | 1894.506 |",
        "| **M\u0026ge;2.7** | 3731.715 | 2294.000 | 11779.000 | 2920.000 | 2660.000 | 1.000 (100.00%) | 0.347 (34.72%) | 1504.841 |",
        "| **M\u0026ge;2.8** | 2964.133 | 1817.000 | 9353.000 | 2320.000 | 2096.000 | 1.000 (100.00%) | 0.347 (34.72%) | 1195.295 |",
        "| **M\u0026ge;2.9** | 2354.386 | 1439.000 | 7427.000 | 1844.000 | 1692.000 | 1.000 (100.00%) | 0.347 (34.72%) | 949.402 |",
        "| **M\u0026ge;3** | 1870.101 | 1139.000 | 5908.000 | 1465.000 | 1333.000 | 1.000 (100.00%) | 0.347 (34.72%) | 754.083 |",
        "| **M\u0026ge;3.1** | 1485.438 | 901.000 | 4688.000 | 1165.000 | 1054.000 | 1.000 (100.00%) | 0.347 (34.72%) | 599.000 |",
        "| **M\u0026ge;3.2** | 1179.801 | 711.000 | 3724.000 | 925.000 | 830.000 | 1.000 (100.00%) | 0.347 (34.72%) | 475.788 |",
        "| **M\u0026ge;3.3** | 937.040 | 561.000 | 2959.000 | 735.000 | 676.000 | 1.000 (100.00%) | 0.347 (34.72%) | 377.915 |",
        "| **M\u0026ge;3.4** | 744.249 | 442.000 | 2353.000 | 585.000 | 525.000 | 1.000 (100.00%) | 0.347 (34.72%) | 300.142 |",
        "| **M\u0026ge;3.5** | 591.058 | 348.000 | 1869.000 | 465.000 | 419.000 | 1.000 (100.00%) | 0.347 (34.72%) | 238.362 |",
        "| **M\u0026ge;3.6** | 469.416 | 273.000 | 1484.000 | 370.000 | 333.000 | 1.000 (100.00%) | 0.347 (34.72%) | 189.299 |",
        "| **M\u0026ge;3.7** | 372.800 | 214.000 | 1179.000 | 294.000 | 258.000 | 1.000 (100.00%) | 0.347 (34.72%) | 150.314 |",
        "| **M\u0026ge;3.8** | 296.085 | 168.000 | 937.000 | 234.000 | 216.000 | 1.000 (100.00%) | 0.347 (34.72%) | 119.372 |",
        "| **M\u0026ge;3.9** | 235.084 | 131.000 | 744.000 | 186.000 | 167.000 | 1.000 (100.00%) | 0.347 (34.72%) | 94.773 |",
        "| **M\u0026ge;4** | 186.682 | 102.000 | 592.000 | 148.000 | 135.000 | 1.000 (100.00%) | 0.347 (34.72%) | 75.251 |",
        "| **M\u0026ge;4.1** | 148.214 | 78.000 | 470.000 | 118.000 | 104.000 | 1.000 (100.00%) | 0.347 (34.72%) | 59.743 |",
        "| **M\u0026ge;4.2** | 117.666 | 61.000 | 376.000 | 94.000 | 84.000 | 1.000 (100.00%) | 0.347 (34.72%) | 47.422 |",
        "| **M\u0026ge;4.3** | 93.400 | 46.000 | 298.000 | 74.000 | 67.000 | 1.000 (100.00%) | 0.347 (34.72%) | 37.647 |",
        "| **M\u0026ge;4.4** | 74.087 | 36.000 | 236.000 | 59.000 | 52.000 | 1.000 (100.00%) | 0.347 (34.72%) | 29.852 |",
        "| **M\u0026ge;4.5** | 58.784 | 27.000 | 188.000 | 47.000 | 40.000 | 1.000 (100.00%) | 0.347 (34.72%) | 23.670 |",
        "| **M\u0026ge;4.6** | 46.603 | 20.000 | 150.000 | 37.000 | 31.000 | 1.000 (100.00%) | 0.347 (34.72%) | 18.757 |",
        "| **M\u0026ge;4.7** | 36.941 | 15.000 | 119.000 | 30.000 | 25.000 | 1.000 (100.00%) | 0.347 (34.72%) | 14.863 |",
        "| **M\u0026ge;4.8** | 29.274 | 11.000 | 95.000 | 23.000 | 21.000 | 1.000 (100.00%) | 0.347 (34.72%) | 11.771 |",
        "| **M\u0026ge;4.9** | 23.169 | 8.000 | 76.000 | 19.000 | 16.000 | 1.000 (100.00%) | 0.347 (34.72%) | 9.307 |",
        "| **M\u0026ge;5** | 18.319 | 6.000 | 60.000 | 15.000 | 13.000 | 1.000 (100.00%) | 0.347 (34.72%) | 7.349 |",
        "| **M\u0026ge;5.1** | 14.465 | 4.000 | 48.000 | 12.000 | 10.000 | 1.000 (99.98%) | 0.347 (34.72%) | 5.789 |",
        "| **M\u0026ge;5.2** | 11.402 | 3.000 | 39.000 | 9.000 | 7.000 | 0.999 (99.89%) | 0.347 (34.72%) | 4.554 |",
        "| **M\u0026ge;5.3** | 8.969 | 2.000 | 31.000 | 7.000 | 5.000 | 0.996 (99.56%) | 0.347 (34.72%) | 3.573 |",
        "| **M\u0026ge;5.4** | 7.047 | 1.000 | 25.000 | 5.000 | 4.000 | 0.987 (98.70%) | 0.347 (34.72%) | 2.799 |",
        "| **M\u0026ge;5.5** | 5.506 | 0.000 | 20.000 | 4.000 | 3.000 | 0.968 (96.79%) | 0.347 (34.72%) | 2.174 |",
        "| **M\u0026ge;5.6** | 4.287 | 0.000 | 16.000 | 3.000 | 2.000 | 0.935 (93.49%) | 0.347 (34.72%) | 1.684 |",
        "| **M\u0026ge;5.7** | 3.319 | 0.000 | 13.000 | 2.000 | 2.000 | 0.883 (88.32%) | 0.347 (34.72%) | 1.294 |",
        "| **M\u0026ge;5.8** | 2.558 | 0.000 | 10.000 | 2.000 | 1.000 | 0.815 (81.50%) | 0.347 (34.72%) | 0.986 |",
        "| **M\u0026ge;5.9** | 1.955 | 0.000 | 8.000 | 1.000 | 1.000 | 0.729 (72.94%) | 0.347 (34.71%) | 0.742 |",
        "| **M\u0026ge;6** | 1.537 | 0.000 | 7.000 | 1.000 | 0.000 | 0.644 (64.44%) | 0.347 (34.70%) | 0.566 |",
        "| **M\u0026ge;6.1** | 1.139 | 0.000 | 6.000 | 1.000 | 0.000 | 0.549 (54.89%) | 0.314 (31.36%) | 0.417 |",
        "| **M\u0026ge;6.2** | 0.780 | 0.000 | 4.000 | 0.000 | 0.000 | 0.430 (43.05%) | 0.263 (26.27%) | 0.280 |",
        "| **M\u0026ge;6.3** | 0.597 | 0.000 | 4.000 | 0.000 | 0.000 | 0.356 (35.64%) | 0.230 (23.03%) | 0.212 |",
        "| **M\u0026ge;6.4** | 0.470 | 0.000 | 3.000 | 0.000 | 0.000 | 0.291 (29.06%) | 0.204 (20.43%) | 0.158 |",
        "| **M\u0026ge;6.5** | 0.366 | 0.000 | 3.000 | 0.000 | 0.000 | 0.237 (23.73%) | 0.180 (18.01%) | 0.122 |",
        "| **M\u0026ge;6.6** | 0.296 | 0.000 | 2.000 | 0.000 | 0.000 | 0.207 (20.71%) | 0.166 (16.61%) | 0.104 |",
        "| **M\u0026ge;6.7** | 0.240 | 0.000 | 2.000 | 0.000 | 0.000 | 0.173 (17.31%) | 0.144 (14.36%) | 0.085 |",
        "| **M\u0026ge;6.8** | 0.194 | 0.000 | 2.000 | 0.000 | 0.000 | 0.148 (14.83%) | 0.128 (12.83%) | 0.070 |",
        "| **M\u0026ge;6.9** | 0.149 | 0.000 | 1.000 | 0.000 | 0.000 | 0.122 (12.17%) | 0.108 (10.81%) | 0.055 |",
        "| **M\u0026ge;7** | 0.118 | 0.000 | 1.000 | 0.000 | 0.000 | 0.100 (9.98%) | 0.091 (9.13%) | 0.043 |",
        "| **M\u0026ge;7.1** | 0.099 | 0.000 | 1.000 | 0.000 | 0.000 | 0.086 (8.63%) | 0.081 (8.14%) | 0.036 |",
        "| **M\u0026ge;7.2** | 0.077 | 0.000 | 1.000 | 0.000 | 0.000 | 0.068 (6.83%) | 0.066 (6.56%) | 0.027 |",
        "| **M\u0026ge;7.3** | 0.056 | 0.000 | 1.000 | 0.000 | 0.000 | 0.051 (5.08%) | 0.050 (4.96%) | 0.019 |",
        "| **M\u0026ge;7.4** | 0.050 | 0.000 | 1.000 | 0.000 | 0.000 | 0.046 (4.59%) | 0.045 (4.54%) | 0.016 |",
        "| **M\u0026ge;7.5** | 0.041 | 0.000 | 1.000 | 0.000 | 0.000 | 0.038 (3.79%) | 0.038 (3.77%) | 0.013 |",
        "| **M\u0026ge;7.6** | 0.021 | 0.000 | 0.000 | 0.000 | 0.000 | 0.020 (1.98%) | 0.020 (1.97%) | 6.71E-3 |",
        "| **M\u0026ge;7.7** | 7.56E-3 | 0.000 | 0.000 | 0.000 | 0.000 | 7.03E-3 (0.70%) | 7.00E-3 (0.70%) | 2.10E-3 |",
        "| **M\u0026ge;7.8** | 4.97E-3 | 0.000 | 0.000 | 0.000 | 0.000 | 4.80E-3 (0.48%) | 4.79E-3 (0.48%) | 1.50E-3 |",
        "| **M\u0026ge;7.9** | 2.96E-3 | 0.000 | 0.000 | 0.000 | 0.000 | 2.94E-3 (0.29%) | 2.94E-3 (0.29%) | 9.00E-4 |",
        "| **M\u0026ge;8** | 1.01E-3 | 0.000 | 0.000 | 0.000 | 0.000 | 1.00E-3 (0.10%) | 1.00E-3 (0.10%) | 2.70E-4 |",
        "| **M\u0026ge;8.1** | 1.70E-4 | 0.000 | 0.000 | 0.000 | 0.000 | 1.70E-4 (0.02%) | 1.70E-4 (0.02%) | 2.00E-5 |",
        "| **M\u0026ge;8.2** | 0.000 | 0.000 | 0.000 | 0.000 | 0.000 | 0.000 (0.00%) | 0.000 (0.00%) | 0.000 |",
        "| **M\u0026ge;8.3** | 0.000 | 0.000 | 0.000 | 0.000 | 0.000 | 0.000 (0.00%) | 0.000 (0.00%) | 0.000 |",
        "| **M\u0026ge;8.4** | 0.000 | 0.000 | 0.000 | 0.000 | 0.000 | 0.000 (0.00%) | 0.000 (0.00%) | 0.000 |",
        "| **M\u0026ge;8.5** | 0.000 | 0.000 | 0.000 | 0.000 | 0.000 | 0.000 (0.00%) | 0.000 (0.00%) | 0.000 |",
        "| **M\u0026ge;8.6** | 0.000 | 0.000 | 0.000 | 0.000 | 0.000 | 0.000 (0.00%) | 0.000 (0.00%) | 0.000 |",
        "| **M\u0026ge;8.7** | 0.000 | 0.000 | 0.000 | 0.000 | 0.000 | 0.000 (0.00%) | 0.000 (0.00%) | 0.000 |",
        "| **M\u0026ge;8.8** | 0.000 | 0.000 | 0.000 | 0.000 | 0.000 | 0.000 (0.00%) | 0.000 (0.00%) | 0.000 |",
        "| **M\u0026ge;8.9** | 0.000 | 0.000 | 0.000 | 0.000 | 0.000 | 0.000 (0.00%) | 0.000 (0.00%) | 0.000 |",
        "| **M\u0026ge;9** | 0.000 | 0.000 | 0.000 | 0.000 | 0.000 | 0.000 (0.00%) | 0.000 (0.00%) | 0.000 |",
        "",
        "### 1 Year Magnitude Number Distribution",
        "*[(top)](#table-of-contents)*",
        "",
        "**Legend**",
        "* **Mean** (thick black line): mean expected number across all 100000 catalogs",
        "* **2.5%,97.5%** (thin black lines): expected number percentiles across all 100000 catalogs",
        "* **Median** (thin blue line): median expected number across all 100000 catalogs",
        "* **Mode** (thin cyan line): modal expected number across all 100000 catalogs",
        "* **1 yr Probability** (thin red line): 1 year probability calculated as the fraction of catalogs with at least 1 occurrence",
        "* **1 yr Supraseismogenic Probability** (thin dashed red line): same as above, but only for supraseismogenic ruptures on explicitly modeled UCERF3 faults",
        "* **95% Conf** (light red shaded region): binomial 95% confidence bounds on probability",
        "* **Primary** (thin green line): mean expected number from primary triggered aftershocks only (no secondary, tertiary, etc...) across all 100000 catalogs",
        "",
        "![MFD Plot](plots/1yr_mag_num_cumulative_triggered.png)",
        "",
        "| Mag | Mean | 2.5 %ile | 97.5 %ile | Median | Mode | 1 yr Probability | 1 yr Supra-Seis Prob | Primary Aftershocks Mean |",
        "|-----|-----|-----|-----|-----|-----|-----|-----|-----|",
        "| **M\u0026ge;2.5** | 4359.416 | 2944.000 | 12952.000 | 3588.000 | 3297.000 | 1.000 (100.00%) | 0.280 (27.96%) | 2078.785 |",
        "| **M\u0026ge;2.6** | 3462.632 | 2333.000 | 10288.000 | 2850.000 | 2615.000 | 1.000 (100.00%) | 0.280 (27.96%) | 1651.091 |",
        "| **M\u0026ge;2.7** | 2750.406 | 1848.000 | 8174.000 | 2265.000 | 2153.000 | 1.000 (100.00%) | 0.280 (27.96%) | 1311.481 |",
        "| **M\u0026ge;2.8** | 2184.681 | 1463.000 | 6495.000 | 1799.000 | 1629.000 | 1.000 (100.00%) | 0.280 (27.96%) | 1041.729 |",
        "| **M\u0026ge;2.9** | 1735.269 | 1158.000 | 5160.000 | 1430.000 | 1321.000 | 1.000 (100.00%) | 0.280 (27.96%) | 827.411 |",
        "| **M\u0026ge;3** | 1378.306 | 915.000 | 4101.000 | 1136.000 | 1047.000 | 1.000 (100.00%) | 0.280 (27.96%) | 657.187 |",
        "| **M\u0026ge;3.1** | 1094.770 | 723.000 | 3254.000 | 903.000 | 835.000 | 1.000 (100.00%) | 0.280 (27.96%) | 522.025 |",
        "| **M\u0026ge;3.2** | 869.568 | 571.000 | 2585.000 | 718.000 | 657.000 | 1.000 (100.00%) | 0.280 (27.96%) | 414.671 |",
        "| **M\u0026ge;3.3** | 690.641 | 449.000 | 2056.000 | 571.000 | 513.000 | 1.000 (100.00%) | 0.280 (27.96%) | 329.369 |",
        "| **M\u0026ge;3.4** | 548.521 | 353.000 | 1632.000 | 454.000 | 410.000 | 1.000 (100.00%) | 0.280 (27.96%) | 261.569 |",
        "| **M\u0026ge;3.5** | 435.618 | 277.000 | 1294.000 | 361.000 | 334.000 | 1.000 (100.00%) | 0.280 (27.96%) | 207.736 |",
        "| **M\u0026ge;3.6** | 345.954 | 217.000 | 1028.000 | 287.000 | 265.000 | 1.000 (100.00%) | 0.280 (27.96%) | 164.975 |",
        "| **M\u0026ge;3.7** | 274.753 | 170.000 | 816.000 | 228.000 | 210.000 | 1.000 (100.00%) | 0.280 (27.96%) | 131.004 |",
        "| **M\u0026ge;3.8** | 218.198 | 133.000 | 648.000 | 182.000 | 169.000 | 1.000 (100.00%) | 0.280 (27.96%) | 104.041 |",
        "| **M\u0026ge;3.9** | 173.248 | 103.000 | 514.000 | 145.000 | 131.000 | 1.000 (100.00%) | 0.280 (27.96%) | 82.604 |",
        "| **M\u0026ge;4** | 137.578 | 80.000 | 409.000 | 115.000 | 109.000 | 1.000 (100.00%) | 0.280 (27.96%) | 65.583 |",
        "| **M\u0026ge;4.1** | 109.222 | 62.000 | 325.000 | 91.000 | 85.000 | 1.000 (100.00%) | 0.280 (27.96%) | 52.065 |",
        "| **M\u0026ge;4.2** | 86.706 | 47.000 | 258.000 | 73.000 | 67.000 | 1.000 (100.00%) | 0.280 (27.96%) | 41.326 |",
        "| **M\u0026ge;4.3** | 68.821 | 36.000 | 205.000 | 58.000 | 53.000 | 1.000 (100.00%) | 0.280 (27.96%) | 32.808 |",
        "| **M\u0026ge;4.4** | 54.577 | 27.000 | 163.000 | 46.000 | 44.000 | 1.000 (100.00%) | 0.280 (27.96%) | 26.011 |",
        "| **M\u0026ge;4.5** | 43.307 | 21.000 | 130.000 | 36.000 | 33.000 | 1.000 (100.00%) | 0.280 (27.96%) | 20.627 |",
        "| **M\u0026ge;4.6** | 34.333 | 15.000 | 103.000 | 29.000 | 27.000 | 1.000 (100.00%) | 0.280 (27.96%) | 16.342 |",
        "| **M\u0026ge;4.7** | 27.214 | 11.000 | 81.000 | 23.000 | 21.000 | 1.000 (100.00%) | 0.280 (27.96%) | 12.951 |",
        "| **M\u0026ge;4.8** | 21.568 | 8.000 | 65.000 | 18.000 | 15.000 | 1.000 (100.00%) | 0.280 (27.96%) | 10.256 |",
        "| **M\u0026ge;4.9** | 17.066 | 6.000 | 52.000 | 14.000 | 13.000 | 1.000 (100.00%) | 0.280 (27.96%) | 8.110 |",
        "| **M\u0026ge;5** | 13.498 | 4.000 | 41.000 | 11.000 | 10.000 | 1.000 (99.98%) | 0.280 (27.96%) | 6.404 |",
        "| **M\u0026ge;5.1** | 10.653 | 3.000 | 33.000 | 9.000 | 8.000 | 0.999 (99.91%) | 0.280 (27.96%) | 5.045 |",
        "| **M\u0026ge;5.2** | 8.397 | 2.000 | 26.000 | 7.000 | 6.000 | 0.996 (99.63%) | 0.280 (27.96%) | 3.970 |",
        "| **M\u0026ge;5.3** | 6.604 | 1.000 | 21.000 | 5.000 | 4.000 | 0.988 (98.81%) | 0.280 (27.96%) | 3.116 |",
        "| **M\u0026ge;5.4** | 5.187 | 0.000 | 17.000 | 4.000 | 3.000 | 0.971 (97.11%) | 0.280 (27.96%) | 2.442 |",
        "| **M\u0026ge;5.5** | 4.052 | 0.000 | 14.000 | 3.000 | 2.000 | 0.939 (93.95%) | 0.280 (27.96%) | 1.897 |",
        "| **M\u0026ge;5.6** | 3.153 | 0.000 | 11.000 | 2.000 | 2.000 | 0.891 (89.15%) | 0.280 (27.96%) | 1.469 |",
        "| **M\u0026ge;5.7** | 2.441 | 0.000 | 9.000 | 2.000 | 1.000 | 0.824 (82.40%) | 0.280 (27.96%) | 1.130 |",
        "| **M\u0026ge;5.8** | 1.880 | 0.000 | 8.000 | 1.000 | 1.000 | 0.742 (74.24%) | 0.280 (27.96%) | 0.860 |",
        "| **M\u0026ge;5.9** | 1.433 | 0.000 | 6.000 | 1.000 | 0.000 | 0.649 (64.95%) | 0.280 (27.95%) | 0.648 |",
        "| **M\u0026ge;6** | 1.121 | 0.000 | 5.000 | 1.000 | 0.000 | 0.560 (56.03%) | 0.279 (27.94%) | 0.494 |",
        "| **M\u0026ge;6.1** | 0.830 | 0.000 | 4.000 | 0.000 | 0.000 | 0.466 (46.60%) | 0.250 (25.03%) | 0.364 |",
        "| **M\u0026ge;6.2** | 0.566 | 0.000 | 3.000 | 0.000 | 0.000 | 0.355 (35.53%) | 0.206 (20.60%) | 0.244 |",
        "| **M\u0026ge;6.3** | 0.432 | 0.000 | 3.000 | 0.000 | 0.000 | 0.289 (28.90%) | 0.179 (17.91%) | 0.185 |",
        "| **M\u0026ge;6.4** | 0.337 | 0.000 | 2.000 | 0.000 | 0.000 | 0.232 (23.19%) | 0.158 (15.77%) | 0.138 |",
        "| **M\u0026ge;6.5** | 0.262 | 0.000 | 2.000 | 0.000 | 0.000 | 0.188 (18.77%) | 0.139 (13.88%) | 0.107 |",
        "| **M\u0026ge;6.6** | 0.214 | 0.000 | 2.000 | 0.000 | 0.000 | 0.163 (16.30%) | 0.128 (12.81%) | 0.091 |",
        "| **M\u0026ge;6.7** | 0.174 | 0.000 | 2.000 | 0.000 | 0.000 | 0.136 (13.57%) | 0.111 (11.09%) | 0.075 |",
        "| **M\u0026ge;6.8** | 0.141 | 0.000 | 1.000 | 0.000 | 0.000 | 0.115 (11.53%) | 0.099 (9.87%) | 0.062 |",
        "| **M\u0026ge;6.9** | 0.109 | 0.000 | 1.000 | 0.000 | 0.000 | 0.094 (9.35%) | 0.082 (8.22%) | 0.049 |",
        "| **M\u0026ge;7** | 0.086 | 0.000 | 1.000 | 0.000 | 0.000 | 0.076 (7.61%) | 0.069 (6.90%) | 0.038 |",
        "| **M\u0026ge;7.1** | 0.072 | 0.000 | 1.000 | 0.000 | 0.000 | 0.065 (6.53%) | 0.061 (6.13%) | 0.032 |",
        "| **M\u0026ge;7.2** | 0.056 | 0.000 | 1.000 | 0.000 | 0.000 | 0.051 (5.10%) | 0.049 (4.89%) | 0.024 |",
        "| **M\u0026ge;7.3** | 0.040 | 0.000 | 1.000 | 0.000 | 0.000 | 0.037 (3.73%) | 0.036 (3.62%) | 0.017 |",
        "| **M\u0026ge;7.4** | 0.036 | 0.000 | 1.000 | 0.000 | 0.000 | 0.033 (3.35%) | 0.033 (3.31%) | 0.015 |",
        "| **M\u0026ge;7.5** | 0.029 | 0.000 | 1.000 | 0.000 | 0.000 | 0.027 (2.74%) | 0.027 (2.73%) | 0.011 |",
        "| **M\u0026ge;7.6** | 0.015 | 0.000 | 0.000 | 0.000 | 0.000 | 0.014 (1.41%) | 0.014 (1.40%) | 5.99E-3 |",
        "| **M\u0026ge;7.7** | 5.25E-3 | 0.000 | 0.000 | 0.000 | 0.000 | 4.94E-3 (0.49%) | 4.93E-3 (0.49%) | 1.82E-3 |",
        "| **M\u0026ge;7.8** | 3.56E-3 | 0.000 | 0.000 | 0.000 | 0.000 | 3.44E-3 (0.34%) | 3.44E-3 (0.34%) | 1.29E-3 |",
        "| **M\u0026ge;7.9** | 2.16E-3 | 0.000 | 0.000 | 0.000 | 0.000 | 2.15E-3 (0.21%) | 2.15E-3 (0.21%) | 7.80E-4 |",
        "| **M\u0026ge;8** | 7.10E-4 | 0.000 | 0.000 | 0.000 | 0.000 | 7.00E-4 (0.07%) | 7.00E-4 (0.07%) | 2.30E-4 |",
        "| **M\u0026ge;8.1** | 1.20E-4 | 0.000 | 0.000 | 0.000 | 0.000 | 1.20E-4 (0.01%) | 1.20E-4 (0.01%) | 1.00E-5 |",
        "| **M\u0026ge;8.2** | 0.000 | 0.000 | 0.000 | 0.000 | 0.000 | 0.000 (0.00%) | 0.000 (0.00%) | 0.000 |",
        "| **M\u0026ge;8.3** | 0.000 | 0.000 | 0.000 | 0.000 | 0.000 | 0.000 (0.00%) | 0.000 (0.00%) | 0.000 |",
        "| **M\u0026ge;8.4** | 0.000 | 0.000 | 0.000 | 0.000 | 0.000 | 0.000 (0.00%) | 0.000 (0.00%) | 0.000 |",
        "| **M\u0026ge;8.5** | 0.000 | 0.000 | 0.000 | 0.000 | 0.000 | 0.000 (0.00%) | 0.000 (0.00%) | 0.000 |",
        "| **M\u0026ge;8.6** | 0.000 | 0.000 | 0.000 | 0.000 | 0.000 | 0.000 (0.00%) | 0.000 (0.00%) | 0.000 |",
        "| **M\u0026ge;8.7** | 0.000 | 0.000 | 0.000 | 0.000 | 0.000 | 0.000 (0.00%) | 0.000 (0.00%) | 0.000 |",
        "| **M\u0026ge;8.8** | 0.000 | 0.000 | 0.000 | 0.000 | 0.000 | 0.000 (0.00%) | 0.000 (0.00%) | 0.000 |",
        "| **M\u0026ge;8.9** | 0.000 | 0.000 | 0.000 | 0.000 | 0.000 | 0.000 (0.00%) | 0.000 (0.00%) | 0.000 |",
        "| **M\u0026ge;9** | 0.000 | 0.000 | 0.000 | 0.000 | 0.000 | 0.000 (0.00%) | 0.000 (0.00%) | 0.000 |",
        "",
        "### 1 Month Magnitude Number Distribution",
        "*[(top)](#table-of-contents)*",
        "",
        "**Legend**",
        "* **Mean** (thick black line): mean expected number across all 100000 catalogs",
        "* **2.5%,97.5%** (thin black lines): expected number percentiles across all 100000 catalogs",
        "* **Median** (thin blue line): median expected number across all 100000 catalogs",
        "* **Mode** (thin cyan line): modal expected number across all 100000 catalogs",
        "* **1 mo Probability** (thin red line): 1 month probability calculated as the fraction of catalogs with at least 1 occurrence",
        "* **1 mo Supraseismogenic Probability** (thin dashed red line): same as above, but only for supraseismogenic ruptures on explicitly modeled UCERF3 faults",
        "* **95% Conf** (light red shaded region): binomial 95% confidence bounds on probability",
        "* **Primary** (thin green line): mean expected number from primary triggered aftershocks only (no secondary, tertiary, etc...) across all 100000 catalogs",
        "",
        "![MFD Plot](plots/1mo_mag_num_cumulative_triggered.png)",
        "",
        "| Mag | Mean | 2.5 %ile | 97.5 %ile | Median | Mode | 1 mo Probability | 1 mo Supra-Seis Prob | Primary Aftershocks Mean |",
        "|-----|-----|-----|-----|-----|-----|-----|-----|-----|",
        "| **M\u0026ge;2.5** | 2953.156 | 2183.000 | 7298.000 | 2558.000 | 2370.000 | 1.000 (100.00%) | 0.205 (20.51%) | 1686.469 |",
        "| **M\u0026ge;2.6** | 2345.599 | 1728.000 | 5812.000 | 2032.000 | 1949.000 | 1.000 (100.00%) | 0.205 (20.51%) | 1339.482 |",
        "| **M\u0026ge;2.7** | 1863.083 | 1369.000 | 4609.000 | 1615.000 | 1519.000 | 1.000 (100.00%) | 0.205 (20.51%) | 1063.957 |",
        "| **M\u0026ge;2.8** | 1479.861 | 1082.000 | 3664.000 | 1284.000 | 1209.000 | 1.000 (100.00%) | 0.205 (20.51%) | 845.100 |",
        "| **M\u0026ge;2.9** | 1175.462 | 855.000 | 2909.000 | 1020.000 | 945.000 | 1.000 (100.00%) | 0.205 (20.51%) | 671.247 |",
        "| **M\u0026ge;3** | 933.673 | 675.000 | 2312.000 | 811.000 | 756.000 | 1.000 (100.00%) | 0.205 (20.51%) | 533.157 |",
        "| **M\u0026ge;3.1** | 741.642 | 532.000 | 1838.000 | 645.000 | 626.000 | 1.000 (100.00%) | 0.205 (20.51%) | 423.515 |",
        "| **M\u0026ge;3.2** | 589.117 | 419.000 | 1457.000 | 513.000 | 489.000 | 1.000 (100.00%) | 0.205 (20.51%) | 336.442 |",
        "| **M\u0026ge;3.3** | 467.912 | 329.000 | 1159.000 | 408.000 | 393.000 | 1.000 (100.00%) | 0.205 (20.51%) | 267.224 |",
        "| **M\u0026ge;3.4** | 371.635 | 258.000 | 921.000 | 324.000 | 309.000 | 1.000 (100.00%) | 0.205 (20.51%) | 212.222 |",
        "| **M\u0026ge;3.5** | 295.137 | 202.000 | 732.000 | 258.000 | 246.000 | 1.000 (100.00%) | 0.205 (20.51%) | 168.548 |",
        "| **M\u0026ge;3.6** | 234.393 | 158.000 | 582.000 | 205.000 | 194.000 | 1.000 (100.00%) | 0.205 (20.51%) | 133.849 |",
        "| **M\u0026ge;3.7** | 186.153 | 123.000 | 462.000 | 163.000 | 150.000 | 1.000 (100.00%) | 0.205 (20.51%) | 106.286 |",
        "| **M\u0026ge;3.8** | 147.846 | 95.000 | 367.000 | 130.000 | 126.000 | 1.000 (100.00%) | 0.205 (20.51%) | 84.418 |",
        "| **M\u0026ge;3.9** | 117.392 | 74.000 | 292.000 | 103.000 | 99.000 | 1.000 (100.00%) | 0.205 (20.51%) | 67.027 |",
        "| **M\u0026ge;4** | 93.217 | 57.000 | 231.000 | 82.000 | 77.000 | 1.000 (100.00%) | 0.205 (20.51%) | 53.218 |",
        "| **M\u0026ge;4.1** | 73.997 | 44.000 | 185.000 | 65.000 | 64.000 | 1.000 (100.00%) | 0.205 (20.51%) | 42.251 |",
        "| **M\u0026ge;4.2** | 58.732 | 33.000 | 148.000 | 52.000 | 47.000 | 1.000 (100.00%) | 0.205 (20.51%) | 33.531 |",
        "| **M\u0026ge;4.3** | 46.614 | 25.000 | 118.000 | 41.000 | 38.000 | 1.000 (100.00%) | 0.205 (20.51%) | 26.619 |",
        "| **M\u0026ge;4.4** | 36.969 | 19.000 | 94.000 | 33.000 | 31.000 | 1.000 (100.00%) | 0.205 (20.51%) | 21.105 |",
        "| **M\u0026ge;4.5** | 29.330 | 14.000 | 75.000 | 26.000 | 24.000 | 1.000 (100.00%) | 0.205 (20.51%) | 16.739 |",
        "| **M\u0026ge;4.6** | 23.246 | 10.000 | 60.000 | 20.000 | 19.000 | 1.000 (100.00%) | 0.205 (20.51%) | 13.261 |",
        "| **M\u0026ge;4.7** | 18.426 | 7.000 | 48.000 | 16.000 | 14.000 | 1.000 (100.00%) | 0.205 (20.51%) | 10.509 |",
        "| **M\u0026ge;4.8** | 14.600 | 5.000 | 38.000 | 13.000 | 12.000 | 1.000 (100.00%) | 0.205 (20.51%) | 8.323 |",
        "| **M\u0026ge;4.9** | 11.553 | 4.000 | 31.000 | 10.000 | 9.000 | 1.000 (99.98%) | 0.205 (20.51%) | 6.584 |",
        "| **M\u0026ge;5** | 9.135 | 2.000 | 25.000 | 8.000 | 7.000 | 0.999 (99.87%) | 0.205 (20.51%) | 5.200 |",
        "| **M\u0026ge;5.1** | 7.206 | 1.000 | 20.000 | 6.000 | 5.000 | 0.995 (99.49%) | 0.205 (20.51%) | 4.096 |",
        "| **M\u0026ge;5.2** | 5.676 | 1.000 | 16.000 | 5.000 | 4.000 | 0.985 (98.49%) | 0.205 (20.51%) | 3.221 |",
        "| **M\u0026ge;5.3** | 4.463 | 0.000 | 13.000 | 4.000 | 3.000 | 0.964 (96.39%) | 0.205 (20.51%) | 2.528 |",
        "| **M\u0026ge;5.4** | 3.502 | 0.000 | 11.000 | 3.000 | 2.000 | 0.930 (93.00%) | 0.205 (20.51%) | 1.980 |",
        "| **M\u0026ge;5.5** | 2.732 | 0.000 | 9.000 | 2.000 | 2.000 | 0.877 (87.67%) | 0.205 (20.51%) | 1.538 |",
        "| **M\u0026ge;5.6** | 2.123 | 0.000 | 7.000 | 2.000 | 1.000 | 0.808 (80.81%) | 0.205 (20.51%) | 1.190 |",
        "| **M\u0026ge;5.7** | 1.642 | 0.000 | 6.000 | 1.000 | 1.000 | 0.725 (72.47%) | 0.205 (20.51%) | 0.916 |",
        "| **M\u0026ge;5.8** | 1.262 | 0.000 | 5.000 | 1.000 | 0.000 | 0.632 (63.16%) | 0.205 (20.51%) | 0.698 |",
        "| **M\u0026ge;5.9** | 0.959 | 0.000 | 4.000 | 1.000 | 0.000 | 0.535 (53.51%) | 0.205 (20.51%) | 0.525 |",
        "| **M\u0026ge;6** | 0.745 | 0.000 | 4.000 | 0.000 | 0.000 | 0.449 (44.87%) | 0.205 (20.51%) | 0.399 |",
        "| **M\u0026ge;6.1** | 0.549 | 0.000 | 3.000 | 0.000 | 0.000 | 0.362 (36.20%) | 0.182 (18.20%) | 0.294 |",
        "| **M\u0026ge;6.2** | 0.372 | 0.000 | 2.000 | 0.000 | 0.000 | 0.268 (26.80%) | 0.147 (14.73%) | 0.197 |",
        "| **M\u0026ge;6.3** | 0.284 | 0.000 | 2.000 | 0.000 | 0.000 | 0.214 (21.44%) | 0.127 (12.74%) | 0.149 |",
        "| **M\u0026ge;6.4** | 0.220 | 0.000 | 2.000 | 0.000 | 0.000 | 0.169 (16.90%) | 0.111 (11.10%) | 0.112 |",
        "| **M\u0026ge;6.5** | 0.171 | 0.000 | 2.000 | 0.000 | 0.000 | 0.135 (13.47%) | 0.098 (9.76%) | 0.087 |",
        "| **M\u0026ge;6.6** | 0.141 | 0.000 | 1.000 | 0.000 | 0.000 | 0.117 (11.66%) | 0.091 (9.05%) | 0.074 |",
        "| **M\u0026ge;6.7** | 0.115 | 0.000 | 1.000 | 0.000 | 0.000 | 0.097 (9.66%) | 0.078 (7.83%) | 0.061 |",
        "| **M\u0026ge;6.8** | 0.094 | 0.000 | 1.000 | 0.000 | 0.000 | 0.082 (8.17%) | 0.070 (6.95%) | 0.051 |",
        "| **M\u0026ge;6.9** | 0.074 | 0.000 | 1.000 | 0.000 | 0.000 | 0.066 (6.58%) | 0.058 (5.76%) | 0.040 |",
        "| **M\u0026ge;7** | 0.058 | 0.000 | 1.000 | 0.000 | 0.000 | 0.053 (5.30%) | 0.048 (4.81%) | 0.031 |",
        "| **M\u0026ge;7.1** | 0.049 | 0.000 | 1.000 | 0.000 | 0.000 | 0.045 (4.53%) | 0.042 (4.24%) | 0.026 |",
        "| **M\u0026ge;7.2** | 0.037 | 0.000 | 1.000 | 0.000 | 0.000 | 0.035 (3.50%) | 0.034 (3.36%) | 0.019 |",
        "| **M\u0026ge;7.3** | 0.027 | 0.000 | 1.000 | 0.000 | 0.000 | 0.025 (2.54%) | 0.025 (2.46%) | 0.014 |",
        "| **M\u0026ge;7.4** | 0.024 | 0.000 | 0.000 | 0.000 | 0.000 | 0.023 (2.27%) | 0.022 (2.24%) | 0.012 |",
        "| **M\u0026ge;7.5** | 0.019 | 0.000 | 0.000 | 0.000 | 0.000 | 0.019 (1.85%) | 0.018 (1.85%) | 9.47E-3 |",
        "| **M\u0026ge;7.6** | 9.82E-3 | 0.000 | 0.000 | 0.000 | 0.000 | 9.44E-3 (0.94%) | 9.41E-3 (0.94%) | 4.93E-3 |",
        "| **M\u0026ge;7.7** | 3.18E-3 | 0.000 | 0.000 | 0.000 | 0.000 | 3.07E-3 (0.31%) | 3.06E-3 (0.31%) | 1.41E-3 |",
        "| **M\u0026ge;7.8** | 2.23E-3 | 0.000 | 0.000 | 0.000 | 0.000 | 2.20E-3 (0.22%) | 2.20E-3 (0.22%) | 9.80E-4 |",
        "| **M\u0026ge;7.9** | 1.33E-3 | 0.000 | 0.000 | 0.000 | 0.000 | 1.33E-3 (0.13%) | 1.33E-3 (0.13%) | 6.10E-4 |",
        "| **M\u0026ge;8** | 4.00E-4 | 0.000 | 0.000 | 0.000 | 0.000 | 4.00E-4 (0.04%) | 4.00E-4 (0.04%) | 1.90E-4 |",
        "| **M\u0026ge;8.1** | 6.00E-5 | 0.000 | 0.000 | 0.000 | 0.000 | 6.00E-5 (0.01%) | 6.00E-5 (0.01%) | 1.00E-5 |",
        "| **M\u0026ge;8.2** | 0.000 | 0.000 | 0.000 | 0.000 | 0.000 | 0.000 (0.00%) | 0.000 (0.00%) | 0.000 |",
        "| **M\u0026ge;8.3** | 0.000 | 0.000 | 0.000 | 0.000 | 0.000 | 0.000 (0.00%) | 0.000 (0.00%) | 0.000 |",
        "| **M\u0026ge;8.4** | 0.000 | 0.000 | 0.000 | 0.000 | 0.000 | 0.000 (0.00%) | 0.000 (0.00%) | 0.000 |",
        "| **M\u0026ge;8.5** | 0.000 | 0.000 | 0.000 | 0.000 | 0.000 | 0.000 (0.00%) | 0.000 (0.00%) | 0.000 |",
        "| **M\u0026ge;8.6** | 0.000 | 0.000 | 0.000 | 0.000 | 0.000 | 0.000 (0.00%) | 0.000 (0.00%) | 0.000 |",
        "| **M\u0026ge;8.7** | 0.000 | 0.000 | 0.000 | 0.000 | 0.000 | 0.000 (0.00%) | 0.000 (0.00%) | 0.000 |",
        "| **M\u0026ge;8.8** | 0.000 | 0.000 | 0.000 | 0.000 | 0.000 | 0.000 (0.00%) | 0.000 (0.00%) | 0.000 |",
        "| **M\u0026ge;8.9** | 0.000 | 0.000 | 0.000 | 0.000 | 0.000 | 0.000 (0.00%) | 0.000 (0.00%) | 0.000 |",
        "| **M\u0026ge;9** | 0.000 | 0.000 | 0.000 | 0.000 | 0.000 | 0.000 (0.00%) | 0.000 (0.00%) | 0.000 |",
        "",
        "### 1 Week Magnitude Number Distribution",
        "*[(top)](#table-of-contents)*",
        "",
        "**Legend**",
        "* **Mean** (thick black line): mean expected number across all 100000 catalogs",
        "* **2.5%,97.5%** (thin black lines): expected number percentiles across all 100000 catalogs",
        "* **Median** (thin blue line): median expected number across all 100000 catalogs",
        "* **Mode** (thin cyan line): modal expected number across all 100000 catalogs",
        "* **1 wk Probability** (thin red line): 1 week probability calculated as the fraction of catalogs with at least 1 occurrence",
        "* **1 wk Supraseismogenic Probability** (thin dashed red line): same as above, but only for supraseismogenic ruptures on explicitly modeled UCERF3 faults",
        "* **95% Conf** (light red shaded region): binomial 95% confidence bounds on probability",
        "* **Primary** (thin green line): mean expected number from primary triggered aftershocks only (no secondary, tertiary, etc...) across all 100000 catalogs",
        "",
        "![MFD Plot](plots/1wk_mag_num_cumulative_triggered.png)",
        "",
        "| Mag | Mean | 2.5 %ile | 97.5 %ile | Median | Mode | 1 wk Probability | 1 wk Supra-Seis Prob | Primary Aftershocks Mean |",
        "|-----|-----|-----|-----|-----|-----|-----|-----|-----|",
        "| **M\u0026ge;2.5** | 2255.508 | 1749.000 | 4643.000 | 2008.000 | 1900.000 | 1.000 (100.00%) | 0.163 (16.35%) | 1428.807 |",
        "| **M\u0026ge;2.6** | 1791.434 | 1383.000 | 3701.000 | 1596.000 | 1502.000 | 1.000 (100.00%) | 0.163 (16.35%) | 1134.797 |",
        "| **M\u0026ge;2.7** | 1422.942 | 1094.000 | 2943.000 | 1268.000 | 1230.000 | 1.000 (100.00%) | 0.163 (16.35%) | 901.386 |",
        "| **M\u0026ge;2.8** | 1130.266 | 864.000 | 2341.000 | 1008.000 | 950.000 | 1.000 (100.00%) | 0.163 (16.35%) | 715.958 |",
        "| **M\u0026ge;2.9** | 897.807 | 682.000 | 1860.000 | 802.000 | 781.000 | 1.000 (100.00%) | 0.163 (16.35%) | 568.671 |",
        "| **M\u0026ge;3** | 713.123 | 538.000 | 1481.000 | 637.000 | 606.000 | 1.000 (100.00%) | 0.163 (16.35%) | 451.694 |",
        "| **M\u0026ge;3.1** | 566.449 | 424.000 | 1180.000 | 506.000 | 475.000 | 1.000 (100.00%) | 0.163 (16.35%) | 358.801 |",
        "| **M\u0026ge;3.2** | 449.979 | 333.000 | 936.000 | 403.000 | 382.000 | 1.000 (100.00%) | 0.163 (16.35%) | 285.037 |",
        "| **M\u0026ge;3.3** | 357.396 | 261.000 | 743.000 | 320.000 | 304.000 | 1.000 (100.00%) | 0.163 (16.35%) | 226.380 |",
        "| **M\u0026ge;3.4** | 283.848 | 204.000 | 594.000 | 255.000 | 241.000 | 1.000 (100.00%) | 0.163 (16.35%) | 179.788 |",
        "| **M\u0026ge;3.5** | 225.427 | 159.000 | 471.000 | 203.000 | 194.000 | 1.000 (100.00%) | 0.163 (16.35%) | 142.802 |",
        "| **M\u0026ge;3.6** | 179.038 | 124.000 | 376.000 | 161.000 | 152.000 | 1.000 (100.00%) | 0.163 (16.35%) | 113.404 |",
        "| **M\u0026ge;3.7** | 142.204 | 96.000 | 300.000 | 128.000 | 122.000 | 1.000 (100.00%) | 0.163 (16.35%) | 90.053 |",
        "| **M\u0026ge;3.8** | 112.933 | 75.000 | 239.000 | 102.000 | 98.000 | 1.000 (100.00%) | 0.163 (16.35%) | 71.524 |",
        "| **M\u0026ge;3.9** | 89.675 | 58.000 | 190.000 | 81.000 | 77.000 | 1.000 (100.00%) | 0.163 (16.35%) | 56.793 |",
        "| **M\u0026ge;4** | 71.209 | 44.000 | 152.000 | 64.000 | 62.000 | 1.000 (100.00%) | 0.163 (16.35%) | 45.092 |",
        "| **M\u0026ge;4.1** | 56.529 | 34.000 | 122.000 | 51.000 | 48.000 | 1.000 (100.00%) | 0.163 (16.35%) | 35.799 |",
        "| **M\u0026ge;4.2** | 44.866 | 25.000 | 97.000 | 41.000 | 38.000 | 1.000 (100.00%) | 0.163 (16.35%) | 28.406 |",
        "| **M\u0026ge;4.3** | 35.604 | 19.000 | 78.000 | 32.000 | 31.000 | 1.000 (100.00%) | 0.163 (16.35%) | 22.549 |",
        "| **M\u0026ge;4.4** | 28.236 | 14.000 | 62.000 | 26.000 | 24.000 | 1.000 (100.00%) | 0.163 (16.35%) | 17.879 |",
        "| **M\u0026ge;4.5** | 22.401 | 10.000 | 50.000 | 20.000 | 19.000 | 1.000 (100.00%) | 0.163 (16.35%) | 14.182 |",
        "| **M\u0026ge;4.6** | 17.756 | 8.000 | 40.000 | 16.000 | 15.000 | 1.000 (100.00%) | 0.163 (16.35%) | 11.238 |",
        "| **M\u0026ge;4.7** | 14.073 | 5.000 | 33.000 | 13.000 | 11.000 | 1.000 (100.00%) | 0.163 (16.35%) | 8.903 |",
        "| **M\u0026ge;4.8** | 11.155 | 4.000 | 27.000 | 10.000 | 9.000 | 1.000 (99.98%) | 0.163 (16.35%) | 7.054 |",
        "| **M\u0026ge;4.9** | 8.827 | 2.000 | 22.000 | 8.000 | 7.000 | 0.999 (99.90%) | 0.163 (16.35%) | 5.582 |",
        "| **M\u0026ge;5** | 6.976 | 1.000 | 18.000 | 6.000 | 5.000 | 0.996 (99.58%) | 0.163 (16.35%) | 4.408 |",
        "| **M\u0026ge;5.1** | 5.501 | 1.000 | 15.000 | 5.000 | 4.000 | 0.987 (98.70%) | 0.163 (16.35%) | 3.470 |",
        "| **M\u0026ge;5.2** | 4.331 | 0.000 | 12.000 | 4.000 | 3.000 | 0.967 (96.74%) | 0.163 (16.35%) | 2.728 |",
        "| **M\u0026ge;5.3** | 3.405 | 0.000 | 10.000 | 3.000 | 2.000 | 0.934 (93.36%) | 0.163 (16.35%) | 2.143 |",
        "| **M\u0026ge;5.4** | 2.670 | 0.000 | 8.000 | 2.000 | 2.000 | 0.883 (88.34%) | 0.163 (16.35%) | 1.679 |",
        "| **M\u0026ge;5.5** | 2.083 | 0.000 | 7.000 | 2.000 | 1.000 | 0.815 (81.49%) | 0.163 (16.35%) | 1.304 |",
        "| **M\u0026ge;5.6** | 1.619 | 0.000 | 6.000 | 1.000 | 1.000 | 0.735 (73.50%) | 0.163 (16.35%) | 1.010 |",
        "| **M\u0026ge;5.7** | 1.249 | 0.000 | 5.000 | 1.000 | 0.000 | 0.644 (64.45%) | 0.163 (16.35%) | 0.776 |",
        "| **M\u0026ge;5.8** | 0.959 | 0.000 | 4.000 | 1.000 | 0.000 | 0.550 (55.03%) | 0.163 (16.35%) | 0.592 |",
        "| **M\u0026ge;5.9** | 0.726 | 0.000 | 3.000 | 0.000 | 0.000 | 0.456 (45.64%) | 0.163 (16.34%) | 0.445 |",
        "| **M\u0026ge;6** | 0.562 | 0.000 | 3.000 | 0.000 | 0.000 | 0.376 (37.64%) | 0.163 (16.34%) | 0.338 |",
        "| **M\u0026ge;6.1** | 0.413 | 0.000 | 2.000 | 0.000 | 0.000 | 0.298 (29.80%) | 0.144 (14.42%) | 0.249 |",
        "| **M\u0026ge;6.2** | 0.279 | 0.000 | 2.000 | 0.000 | 0.000 | 0.216 (21.59%) | 0.116 (11.57%) | 0.166 |",
        "| **M\u0026ge;6.3** | 0.213 | 0.000 | 2.000 | 0.000 | 0.000 | 0.171 (17.15%) | 0.100 (9.96%) | 0.126 |",
        "| **M\u0026ge;6.4** | 0.164 | 0.000 | 1.000 | 0.000 | 0.000 | 0.134 (13.38%) | 0.087 (8.65%) | 0.094 |",
        "| **M\u0026ge;6.5** | 0.127 | 0.000 | 1.000 | 0.000 | 0.000 | 0.106 (10.60%) | 0.076 (7.62%) | 0.073 |",
        "| **M\u0026ge;6.6** | 0.106 | 0.000 | 1.000 | 0.000 | 0.000 | 0.092 (9.20%) | 0.071 (7.08%) | 0.063 |",
        "| **M\u0026ge;6.7** | 0.087 | 0.000 | 1.000 | 0.000 | 0.000 | 0.076 (7.62%) | 0.061 (6.13%) | 0.052 |",
        "| **M\u0026ge;6.8** | 0.072 | 0.000 | 1.000 | 0.000 | 0.000 | 0.064 (6.42%) | 0.054 (5.44%) | 0.043 |",
        "| **M\u0026ge;6.9** | 0.056 | 0.000 | 1.000 | 0.000 | 0.000 | 0.052 (5.16%) | 0.045 (4.51%) | 0.035 |",
        "| **M\u0026ge;7** | 0.044 | 0.000 | 1.000 | 0.000 | 0.000 | 0.041 (4.12%) | 0.037 (3.73%) | 0.027 |",
        "| **M\u0026ge;7.1** | 0.037 | 0.000 | 1.000 | 0.000 | 0.000 | 0.035 (3.48%) | 0.033 (3.26%) | 0.022 |",
        "| **M\u0026ge;7.2** | 0.028 | 0.000 | 1.000 | 0.000 | 0.000 | 0.027 (2.70%) | 0.026 (2.58%) | 0.017 |",
        "| **M\u0026ge;7.3** | 0.020 | 0.000 | 0.000 | 0.000 | 0.000 | 0.019 (1.94%) | 0.019 (1.88%) | 0.012 |",
        "| **M\u0026ge;7.4** | 0.018 | 0.000 | 0.000 | 0.000 | 0.000 | 0.017 (1.72%) | 0.017 (1.70%) | 0.010 |",
        "| **M\u0026ge;7.5** | 0.015 | 0.000 | 0.000 | 0.000 | 0.000 | 0.014 (1.42%) | 0.014 (1.41%) | 8.24E-3 |",
        "| **M\u0026ge;7.6** | 7.57E-3 | 0.000 | 0.000 | 0.000 | 0.000 | 7.32E-3 (0.73%) | 7.30E-3 (0.73%) | 4.31E-3 |",
        "| **M\u0026ge;7.7** | 2.42E-3 | 0.000 | 0.000 | 0.000 | 0.000 | 2.34E-3 (0.23%) | 2.34E-3 (0.23%) | 1.25E-3 |",
        "| **M\u0026ge;7.8** | 1.70E-3 | 0.000 | 0.000 | 0.000 | 0.000 | 1.68E-3 (0.17%) | 1.68E-3 (0.17%) | 8.70E-4 |",
        "| **M\u0026ge;7.9** | 1.03E-3 | 0.000 | 0.000 | 0.000 | 0.000 | 1.03E-3 (0.10%) | 1.03E-3 (0.10%) | 5.40E-4 |",
        "| **M\u0026ge;8** | 2.90E-4 | 0.000 | 0.000 | 0.000 | 0.000 | 2.90E-4 (0.03%) | 2.90E-4 (0.03%) | 1.60E-4 |",
        "| **M\u0026ge;8.1** | 4.00E-5 | 0.000 | 0.000 | 0.000 | 0.000 | 4.00E-5 (0.00%) | 4.00E-5 (0.00%) | 1.00E-5 |",
        "| **M\u0026ge;8.2** | 0.000 | 0.000 | 0.000 | 0.000 | 0.000 | 0.000 (0.00%) | 0.000 (0.00%) | 0.000 |",
        "| **M\u0026ge;8.3** | 0.000 | 0.000 | 0.000 | 0.000 | 0.000 | 0.000 (0.00%) | 0.000 (0.00%) | 0.000 |",
        "| **M\u0026ge;8.4** | 0.000 | 0.000 | 0.000 | 0.000 | 0.000 | 0.000 (0.00%) | 0.000 (0.00%) | 0.000 |",
        "| **M\u0026ge;8.5** | 0.000 | 0.000 | 0.000 | 0.000 | 0.000 | 0.000 (0.00%) | 0.000 (0.00%) | 0.000 |",
        "| **M\u0026ge;8.6** | 0.000 | 0.000 | 0.000 | 0.000 | 0.000 | 0.000 (0.00%) | 0.000 (0.00%) | 0.000 |",
        "| **M\u0026ge;8.7** | 0.000 | 0.000 | 0.000 | 0.000 | 0.000 | 0.000 (0.00%) | 0.000 (0.00%) | 0.000 |",
        "| **M\u0026ge;8.8** | 0.000 | 0.000 | 0.000 | 0.000 | 0.000 | 0.000 (0.00%) | 0.000 (0.00%) | 0.000 |",
        "| **M\u0026ge;8.9** | 0.000 | 0.000 | 0.000 | 0.000 | 0.000 | 0.000 (0.00%) | 0.000 (0.00%) | 0.000 |",
        "| **M\u0026ge;9** | 0.000 | 0.000 | 0.000 | 0.000 | 0.000 | 0.000 (0.00%) | 0.000 (0.00%) | 0.000 |",
        "",
        "### 1 Day Magnitude Number Distribution",
        "*[(top)](#table-of-contents)*",
        "",
        "**Legend**",
        "* **Mean** (thick black line): mean expected number across all 100000 catalogs",
        "* **2.5%,97.5%** (thin black lines): expected number percentiles across all 100000 catalogs",
        "* **Median** (thin blue line): median expected number across all 100000 catalogs",
        "* **Mode** (thin cyan line): modal expected number across all 100000 catalogs",
        "* **1 d Probability** (thin red line): 1 day probability calculated as the fraction of catalogs with at least 1 occurrence",
        "* **1 d Supraseismogenic Probability** (thin dashed red line): same as above, but only for supraseismogenic ruptures on explicitly modeled UCERF3 faults",
        "* **95% Conf** (light red shaded region): binomial 95% confidence bounds on probability",
        "* **Primary** (thin green line): mean expected number from primary triggered aftershocks only (no secondary, tertiary, etc...) across all 100000 catalogs",
        "",
        "![MFD Plot](plots/1d_mag_num_cumulative_triggered.png)",
        "",
        "| Mag | Mean | 2.5 %ile | 97.5 %ile | Median | Mode | 1 d Probability | 1 d Supra-Seis Prob | Primary Aftershocks Mean |",
        "|-----|-----|-----|-----|-----|-----|-----|-----|-----|",
        "| **M\u0026ge;2.5** | 1462.144 | 1201.000 | 2564.000 | 1349.000 | 1311.000 | 1.000 (100.00%) | 0.112 (11.15%) | 1063.787 |",
        "| **M\u0026ge;2.6** | 1161.303 | 948.000 | 2034.000 | 1072.000 | 1050.000 | 1.000 (100.00%) | 0.112 (11.15%) | 844.912 |",
        "| **M\u0026ge;2.7** | 922.419 | 748.000 | 1618.000 | 852.000 | 836.000 | 1.000 (100.00%) | 0.112 (11.15%) | 671.132 |",
        "| **M\u0026ge;2.8** | 732.716 | 590.000 | 1285.000 | 677.000 | 651.000 | 1.000 (100.00%) | 0.112 (11.15%) | 533.111 |",
        "| **M\u0026ge;2.9** | 582.023 | 465.000 | 1022.000 | 539.000 | 511.000 | 1.000 (100.00%) | 0.112 (11.15%) | 423.462 |",
        "| **M\u0026ge;3** | 462.311 | 365.000 | 809.000 | 428.000 | 417.000 | 1.000 (100.00%) | 0.112 (11.15%) | 336.366 |",
        "| **M\u0026ge;3.1** | 367.231 | 287.000 | 646.000 | 341.000 | 330.000 | 1.000 (100.00%) | 0.112 (11.15%) | 267.199 |",
        "| **M\u0026ge;3.2** | 291.704 | 225.000 | 514.000 | 271.000 | 261.000 | 1.000 (100.00%) | 0.112 (11.15%) | 212.251 |",
        "| **M\u0026ge;3.3** | 231.687 | 176.000 | 409.000 | 215.000 | 209.000 | 1.000 (100.00%) | 0.112 (11.15%) | 168.586 |",
        "| **M\u0026ge;3.4** | 184.009 | 137.000 | 325.000 | 171.000 | 167.000 | 1.000 (100.00%) | 0.112 (11.15%) | 133.894 |",
        "| **M\u0026ge;3.5** | 146.134 | 106.000 | 258.000 | 136.000 | 130.000 | 1.000 (100.00%) | 0.112 (11.15%) | 106.343 |",
        "| **M\u0026ge;3.6** | 116.048 | 82.000 | 205.000 | 108.000 | 103.000 | 1.000 (100.00%) | 0.112 (11.15%) | 84.450 |",
        "| **M\u0026ge;3.7** | 92.171 | 64.000 | 164.000 | 86.000 | 82.000 | 1.000 (100.00%) | 0.112 (11.15%) | 67.070 |",
        "| **M\u0026ge;3.8** | 73.191 | 49.000 | 130.000 | 68.000 | 66.000 | 1.000 (100.00%) | 0.112 (11.15%) | 53.269 |",
        "| **M\u0026ge;3.9** | 58.126 | 37.000 | 104.000 | 54.000 | 53.000 | 1.000 (100.00%) | 0.112 (11.15%) | 42.303 |",
        "| **M\u0026ge;4** | 46.156 | 28.000 | 83.000 | 43.000 | 42.000 | 1.000 (100.00%) | 0.112 (11.15%) | 33.594 |",
        "| **M\u0026ge;4.1** | 36.644 | 21.000 | 67.000 | 34.000 | 33.000 | 1.000 (100.00%) | 0.112 (11.15%) | 26.671 |",
        "| **M\u0026ge;4.2** | 29.081 | 16.000 | 54.000 | 27.000 | 26.000 | 1.000 (100.00%) | 0.112 (11.15%) | 21.164 |",
        "| **M\u0026ge;4.3** | 23.083 | 12.000 | 43.000 | 22.000 | 21.000 | 1.000 (100.00%) | 0.112 (11.15%) | 16.800 |",
        "| **M\u0026ge;4.4** | 18.298 | 9.000 | 35.000 | 17.000 | 16.000 | 1.000 (100.00%) | 0.112 (11.15%) | 13.316 |",
        "| **M\u0026ge;4.5** | 14.511 | 6.000 | 29.000 | 13.000 | 13.000 | 1.000 (100.00%) | 0.112 (11.15%) | 10.560 |",
        "| **M\u0026ge;4.6** | 11.501 | 4.000 | 24.000 | 11.000 | 10.000 | 1.000 (99.99%) | 0.112 (11.15%) | 8.369 |",
        "| **M\u0026ge;4.7** | 9.114 | 3.000 | 19.000 | 8.000 | 8.000 | 0.999 (99.94%) | 0.112 (11.15%) | 6.632 |",
        "| **M\u0026ge;4.8** | 7.222 | 2.000 | 16.000 | 7.000 | 6.000 | 0.997 (99.74%) | 0.112 (11.15%) | 5.255 |",
        "| **M\u0026ge;4.9** | 5.710 | 1.000 | 13.000 | 5.000 | 5.000 | 0.992 (99.16%) | 0.112 (11.15%) | 4.155 |",
        "| **M\u0026ge;5** | 4.509 | 1.000 | 11.000 | 4.000 | 3.000 | 0.978 (97.78%) | 0.112 (11.15%) | 3.279 |",
        "| **M\u0026ge;5.1** | 3.554 | 0.000 | 9.000 | 3.000 | 3.000 | 0.951 (95.08%) | 0.112 (11.15%) | 2.582 |",
        "| **M\u0026ge;5.2** | 2.800 | 0.000 | 8.000 | 2.000 | 2.000 | 0.908 (90.84%) | 0.112 (11.15%) | 2.031 |",
        "| **M\u0026ge;5.3** | 2.202 | 0.000 | 7.000 | 2.000 | 1.000 | 0.849 (84.94%) | 0.112 (11.15%) | 1.597 |",
        "| **M\u0026ge;5.4** | 1.726 | 0.000 | 6.000 | 1.000 | 1.000 | 0.777 (77.67%) | 0.112 (11.15%) | 1.251 |",
        "| **M\u0026ge;5.5** | 1.346 | 0.000 | 5.000 | 1.000 | 1.000 | 0.690 (68.99%) | 0.112 (11.15%) | 0.970 |",
        "| **M\u0026ge;5.6** | 1.046 | 0.000 | 4.000 | 1.000 | 0.000 | 0.600 (59.97%) | 0.111 (11.15%) | 0.752 |",
        "| **M\u0026ge;5.7** | 0.806 | 0.000 | 3.000 | 1.000 | 0.000 | 0.508 (50.80%) | 0.111 (11.15%) | 0.578 |",
        "| **M\u0026ge;5.8** | 0.616 | 0.000 | 3.000 | 0.000 | 0.000 | 0.420 (41.98%) | 0.111 (11.15%) | 0.440 |",
        "| **M\u0026ge;5.9** | 0.466 | 0.000 | 2.000 | 0.000 | 0.000 | 0.339 (33.91%) | 0.111 (11.15%) | 0.330 |",
        "| **M\u0026ge;6** | 0.357 | 0.000 | 2.000 | 0.000 | 0.000 | 0.272 (27.22%) | 0.111 (11.14%) | 0.251 |",
        "| **M\u0026ge;6.1** | 0.262 | 0.000 | 2.000 | 0.000 | 0.000 | 0.210 (21.04%) | 0.098 (9.78%) | 0.184 |",
        "| **M\u0026ge;6.2** | 0.175 | 0.000 | 1.000 | 0.000 | 0.000 | 0.148 (14.78%) | 0.077 (7.70%) | 0.122 |",
        "| **M\u0026ge;6.3** | 0.134 | 0.000 | 1.000 | 0.000 | 0.000 | 0.116 (11.59%) | 0.066 (6.62%) | 0.093 |",
        "| **M\u0026ge;6.4** | 0.102 | 0.000 | 1.000 | 0.000 | 0.000 | 0.089 (8.90%) | 0.057 (5.74%) | 0.069 |",
        "| **M\u0026ge;6.5** | 0.079 | 0.000 | 1.000 | 0.000 | 0.000 | 0.070 (7.01%) | 0.051 (5.06%) | 0.054 |",
        "| **M\u0026ge;6.6** | 0.067 | 0.000 | 1.000 | 0.000 | 0.000 | 0.061 (6.09%) | 0.047 (4.72%) | 0.047 |",
        "| **M\u0026ge;6.7** | 0.055 | 0.000 | 1.000 | 0.000 | 0.000 | 0.051 (5.08%) | 0.041 (4.11%) | 0.039 |",
        "| **M\u0026ge;6.8** | 0.046 | 0.000 | 1.000 | 0.000 | 0.000 | 0.043 (4.27%) | 0.036 (3.63%) | 0.033 |",
        "| **M\u0026ge;6.9** | 0.036 | 0.000 | 1.000 | 0.000 | 0.000 | 0.034 (3.43%) | 0.030 (3.01%) | 0.026 |",
        "| **M\u0026ge;7** | 0.029 | 0.000 | 1.000 | 0.000 | 0.000 | 0.027 (2.73%) | 0.025 (2.48%) | 0.020 |",
        "| **M\u0026ge;7.1** | 0.024 | 0.000 | 0.000 | 0.000 | 0.000 | 0.023 (2.30%) | 0.022 (2.16%) | 0.017 |",
        "| **M\u0026ge;7.2** | 0.018 | 0.000 | 0.000 | 0.000 | 0.000 | 0.018 (1.77%) | 0.017 (1.70%) | 0.013 |",
        "| **M\u0026ge;7.3** | 0.013 | 0.000 | 0.000 | 0.000 | 0.000 | 0.013 (1.26%) | 0.012 (1.23%) | 8.90E-3 |",
        "| **M\u0026ge;7.4** | 0.011 | 0.000 | 0.000 | 0.000 | 0.000 | 0.011 (1.12%) | 0.011 (1.11%) | 7.88E-3 |",
        "| **M\u0026ge;7.5** | 9.45E-3 | 0.000 | 0.000 | 0.000 | 0.000 | 9.26E-3 (0.93%) | 9.23E-3 (0.92%) | 6.38E-3 |",
        "| **M\u0026ge;7.6** | 4.93E-3 | 0.000 | 0.000 | 0.000 | 0.000 | 4.83E-3 (0.48%) | 4.82E-3 (0.48%) | 3.37E-3 |",
        "| **M\u0026ge;7.7** | 1.58E-3 | 0.000 | 0.000 | 0.000 | 0.000 | 1.54E-3 (0.15%) | 1.54E-3 (0.15%) | 9.60E-4 |",
        "| **M\u0026ge;7.8** | 1.08E-3 | 0.000 | 0.000 | 0.000 | 0.000 | 1.08E-3 (0.11%) | 1.08E-3 (0.11%) | 6.60E-4 |",
        "| **M\u0026ge;7.9** | 6.00E-4 | 0.000 | 0.000 | 0.000 | 0.000 | 6.00E-4 (0.06%) | 6.00E-4 (0.06%) | 3.70E-4 |",
        "| **M\u0026ge;8** | 1.60E-4 | 0.000 | 0.000 | 0.000 | 0.000 | 1.60E-4 (0.02%) | 1.60E-4 (0.02%) | 1.00E-4 |",
        "| **M\u0026ge;8.1** | 0.000 | 0.000 | 0.000 | 0.000 | 0.000 | 0.000 (0.00%) | 0.000 (0.00%) | 0.000 |",
        "| **M\u0026ge;8.2** | 0.000 | 0.000 | 0.000 | 0.000 | 0.000 | 0.000 (0.00%) | 0.000 (0.00%) | 0.000 |",
        "| **M\u0026ge;8.3** | 0.000 | 0.000 | 0.000 | 0.000 | 0.000 | 0.000 (0.00%) | 0.000 (0.00%) | 0.000 |",
        "| **M\u0026ge;8.4** | 0.000 | 0.000 | 0.000 | 0.000 | 0.000 | 0.000 (0.00%) | 0.000 (0.00%) | 0.000 |",
        "| **M\u0026ge;8.5** | 0.000 | 0.000 | 0.000 | 0.000 | 0.000 | 0.000 (0.00%) | 0.000 (0.00%) | 0.000 |",
        "| **M\u0026ge;8.6** | 0.000 | 0.000 | 0.000 | 0.000 | 0.000 | 0.000 (0.00%) | 0.000 (0.00%) | 0.000 |",
        "| **M\u0026ge;8.7** | 0.000 | 0.000 | 0.000 | 0.000 | 0.000 | 0.000 (0.00%) | 0.000 (0.00%) | 0.000 |",
        "| **M\u0026ge;8.8** | 0.000 | 0.000 | 0.000 | 0.000 | 0.000 | 0.000 (0.00%) | 0.000 (0.00%) | 0.000 |",
        "| **M\u0026ge;8.9** | 0.000 | 0.000 | 0.000 | 0.000 | 0.000 | 0.000 (0.00%) | 0.000 (0.00%) | 0.000 |",
        "| **M\u0026ge;9** | 0.000 | 0.000 | 0.000 | 0.000 | 0.000 | 0.000 (0.00%) | 0.000 (0.00%) | 0.000 |",
        "",
        "### 1 Hour Magnitude Number Distribution",
        "*[(top)](#table-of-contents)*",
        "",
        "**Legend**",
        "* **Mean** (thick black line): mean expected number across all 100000 catalogs",
        "* **2.5%,97.5%** (thin black lines): expected number percentiles across all 100000 catalogs",
        "* **Median** (thin blue line): median expected number across all 100000 catalogs",
        "* **Mode** (thin cyan line): modal expected number across all 100000 catalogs",
        "* **1 hr Probability** (thin red line): 1 hour probability calculated as the fraction of catalogs with at least 1 occurrence",
        "* **1 hr Supraseismogenic Probability** (thin dashed red line): same as above, but only for supraseismogenic ruptures on explicitly modeled UCERF3 faults",
        "* **95% Conf** (light red shaded region): binomial 95% confidence bounds on probability",
        "* **Primary** (thin green line): mean expected number from primary triggered aftershocks only (no secondary, tertiary, etc...) across all 100000 catalogs",
        "",
        "![MFD Plot](plots/1hr_mag_num_cumulative_triggered.png)",
        "",
        "| Mag | Mean | 2.5 %ile | 97.5 %ile | Median | Mode | 1 hr Probability | 1 hr Supra-Seis Prob | Primary Aftershocks Mean |",
        "|-----|-----|-----|-----|-----|-----|-----|-----|-----|",
        "| **M\u0026ge;2.5** | 508.030 | 444.000 | 614.000 | 496.000 | 490.000 | 1.000 (100.00%) | 0.041 (4.11%) | 457.602 |",
        "| **M\u0026ge;2.6** | 403.501 | 349.000 | 490.000 | 394.000 | 387.000 | 1.000 (100.00%) | 0.041 (4.11%) | 363.448 |",
        "| **M\u0026ge;2.7** | 320.526 | 273.000 | 391.000 | 313.000 | 310.000 | 1.000 (100.00%) | 0.041 (4.11%) | 288.708 |",
        "| **M\u0026ge;2.8** | 254.618 | 214.000 | 312.000 | 249.000 | 246.000 | 1.000 (100.00%) | 0.041 (4.11%) | 229.340 |",
        "| **M\u0026ge;2.9** | 202.266 | 167.000 | 250.000 | 198.000 | 195.000 | 1.000 (100.00%) | 0.041 (4.11%) | 182.184 |",
        "| **M\u0026ge;3** | 160.650 | 130.000 | 201.000 | 157.000 | 158.000 | 1.000 (100.00%) | 0.041 (4.11%) | 144.707 |",
        "| **M\u0026ge;3.1** | 127.611 | 101.000 | 162.000 | 125.000 | 123.000 | 1.000 (100.00%) | 0.041 (4.11%) | 114.954 |",
        "| **M\u0026ge;3.2** | 101.372 | 78.000 | 130.000 | 99.000 | 99.000 | 1.000 (100.00%) | 0.041 (4.11%) | 91.323 |",
        "| **M\u0026ge;3.3** | 80.504 | 61.000 | 105.000 | 79.000 | 79.000 | 1.000 (100.00%) | 0.041 (4.11%) | 72.522 |",
        "| **M\u0026ge;3.4** | 63.930 | 46.000 | 86.000 | 63.000 | 62.000 | 1.000 (100.00%) | 0.041 (4.11%) | 57.590 |",
        "| **M\u0026ge;3.5** | 50.774 | 36.000 | 70.000 | 50.000 | 48.000 | 1.000 (100.00%) | 0.041 (4.11%) | 45.742 |",
        "| **M\u0026ge;3.6** | 40.326 | 27.000 | 57.000 | 39.000 | 39.000 | 1.000 (100.00%) | 0.041 (4.11%) | 36.331 |",
        "| **M\u0026ge;3.7** | 32.032 | 20.000 | 46.000 | 31.000 | 30.000 | 1.000 (100.00%) | 0.041 (4.11%) | 28.851 |",
        "| **M\u0026ge;3.8** | 25.445 | 15.000 | 38.000 | 25.000 | 24.000 | 1.000 (100.00%) | 0.041 (4.11%) | 22.921 |",
        "| **M\u0026ge;3.9** | 20.211 | 11.000 | 31.000 | 20.000 | 19.000 | 1.000 (100.00%) | 0.041 (4.11%) | 18.208 |",
        "| **M\u0026ge;4** | 16.050 | 8.000 | 26.000 | 16.000 | 15.000 | 1.000 (100.00%) | 0.041 (4.11%) | 14.459 |",
        "| **M\u0026ge;4.1** | 12.740 | 6.000 | 21.000 | 12.000 | 12.000 | 1.000 (100.00%) | 0.041 (4.11%) | 11.479 |",
        "| **M\u0026ge;4.2** | 10.115 | 4.000 | 18.000 | 10.000 | 9.000 | 1.000 (99.99%) | 0.041 (4.11%) | 9.113 |",
        "| **M\u0026ge;4.3** | 8.026 | 3.000 | 15.000 | 8.000 | 7.000 | 0.999 (99.93%) | 0.041 (4.11%) | 7.234 |",
        "| **M\u0026ge;4.4** | 6.364 | 2.000 | 12.000 | 6.000 | 6.000 | 0.997 (99.73%) | 0.041 (4.11%) | 5.735 |",
        "| **M\u0026ge;4.5** | 5.044 | 1.000 | 10.000 | 5.000 | 4.000 | 0.991 (99.12%) | 0.041 (4.11%) | 4.545 |",
        "| **M\u0026ge;4.6** | 3.997 | 1.000 | 9.000 | 4.000 | 3.000 | 0.977 (97.72%) | 0.041 (4.11%) | 3.603 |",
        "| **M\u0026ge;4.7** | 3.165 | 0.000 | 7.000 | 3.000 | 3.000 | 0.951 (95.08%) | 0.041 (4.11%) | 2.853 |",
        "| **M\u0026ge;4.8** | 2.507 | 0.000 | 6.000 | 2.000 | 2.000 | 0.908 (90.79%) | 0.041 (4.11%) | 2.260 |",
        "| **M\u0026ge;4.9** | 1.982 | 0.000 | 5.000 | 2.000 | 1.000 | 0.849 (84.85%) | 0.041 (4.11%) | 1.788 |",
        "| **M\u0026ge;5** | 1.568 | 0.000 | 5.000 | 1.000 | 1.000 | 0.775 (77.52%) | 0.041 (4.11%) | 1.414 |",
        "| **M\u0026ge;5.1** | 1.236 | 0.000 | 4.000 | 1.000 | 1.000 | 0.691 (69.12%) | 0.041 (4.11%) | 1.115 |",
        "| **M\u0026ge;5.2** | 0.970 | 0.000 | 3.000 | 1.000 | 0.000 | 0.604 (60.39%) | 0.041 (4.11%) | 0.875 |",
        "| **M\u0026ge;5.3** | 0.764 | 0.000 | 3.000 | 1.000 | 0.000 | 0.519 (51.85%) | 0.041 (4.11%) | 0.689 |",
        "| **M\u0026ge;5.4** | 0.600 | 0.000 | 3.000 | 0.000 | 0.000 | 0.438 (43.77%) | 0.041 (4.11%) | 0.540 |",
        "| **M\u0026ge;5.5** | 0.467 | 0.000 | 2.000 | 0.000 | 0.000 | 0.361 (36.15%) | 0.041 (4.11%) | 0.420 |",
        "| **M\u0026ge;5.6** | 0.363 | 0.000 | 2.000 | 0.000 | 0.000 | 0.295 (29.54%) | 0.041 (4.11%) | 0.327 |",
        "| **M\u0026ge;5.7** | 0.279 | 0.000 | 2.000 | 0.000 | 0.000 | 0.236 (23.60%) | 0.041 (4.11%) | 0.251 |",
        "| **M\u0026ge;5.8** | 0.213 | 0.000 | 1.000 | 0.000 | 0.000 | 0.186 (18.61%) | 0.041 (4.11%) | 0.192 |",
        "| **M\u0026ge;5.9** | 0.160 | 0.000 | 1.000 | 0.000 | 0.000 | 0.143 (14.33%) | 0.041 (4.11%) | 0.143 |",
        "| **M\u0026ge;6** | 0.122 | 0.000 | 1.000 | 0.000 | 0.000 | 0.111 (11.11%) | 0.041 (4.11%) | 0.109 |",
        "| **M\u0026ge;6.1** | 0.089 | 0.000 | 1.000 | 0.000 | 0.000 | 0.083 (8.31%) | 0.036 (3.61%) | 0.080 |",
        "| **M\u0026ge;6.2** | 0.059 | 0.000 | 1.000 | 0.000 | 0.000 | 0.056 (5.60%) | 0.028 (2.79%) | 0.053 |",
        "| **M\u0026ge;6.3** | 0.045 | 0.000 | 1.000 | 0.000 | 0.000 | 0.043 (4.32%) | 0.024 (2.38%) | 0.040 |",
        "| **M\u0026ge;6.4** | 0.034 | 0.000 | 1.000 | 0.000 | 0.000 | 0.033 (3.27%) | 0.021 (2.06%) | 0.030 |",
        "| **M\u0026ge;6.5** | 0.026 | 0.000 | 1.000 | 0.000 | 0.000 | 0.025 (2.53%) | 0.018 (1.79%) | 0.023 |",
        "| **M\u0026ge;6.6** | 0.023 | 0.000 | 0.000 | 0.000 | 0.000 | 0.022 (2.20%) | 0.017 (1.67%) | 0.020 |",
        "| **M\u0026ge;6.7** | 0.019 | 0.000 | 0.000 | 0.000 | 0.000 | 0.018 (1.85%) | 0.015 (1.48%) | 0.017 |",
        "| **M\u0026ge;6.8** | 0.016 | 0.000 | 0.000 | 0.000 | 0.000 | 0.015 (1.54%) | 0.013 (1.29%) | 0.014 |",
        "| **M\u0026ge;6.9** | 0.012 | 0.000 | 0.000 | 0.000 | 0.000 | 0.012 (1.22%) | 0.011 (1.05%) | 0.011 |",
        "| **M\u0026ge;7** | 9.67E-3 | 0.000 | 0.000 | 0.000 | 0.000 | 9.53E-3 (0.95%) | 8.52E-3 (0.85%) | 8.77E-3 |",
        "| **M\u0026ge;7.1** | 8.07E-3 | 0.000 | 0.000 | 0.000 | 0.000 | 7.97E-3 (0.80%) | 7.39E-3 (0.74%) | 7.32E-3 |",
        "| **M\u0026ge;7.2** | 6.05E-3 | 0.000 | 0.000 | 0.000 | 0.000 | 6.00E-3 (0.60%) | 5.76E-3 (0.58%) | 5.49E-3 |",
        "| **M\u0026ge;7.3** | 4.20E-3 | 0.000 | 0.000 | 0.000 | 0.000 | 4.18E-3 (0.42%) | 4.10E-3 (0.41%) | 3.80E-3 |",
        "| **M\u0026ge;7.4** | 3.69E-3 | 0.000 | 0.000 | 0.000 | 0.000 | 3.67E-3 (0.37%) | 3.66E-3 (0.37%) | 3.31E-3 |",
        "| **M\u0026ge;7.5** | 2.96E-3 | 0.000 | 0.000 | 0.000 | 0.000 | 2.94E-3 (0.29%) | 2.94E-3 (0.29%) | 2.63E-3 |",
        "| **M\u0026ge;7.6** | 1.54E-3 | 0.000 | 0.000 | 0.000 | 0.000 | 1.54E-3 (0.15%) | 1.54E-3 (0.15%) | 1.38E-3 |",
        "| **M\u0026ge;7.7** | 4.90E-4 | 0.000 | 0.000 | 0.000 | 0.000 | 4.90E-4 (0.05%) | 4.90E-4 (0.05%) | 4.40E-4 |",
        "| **M\u0026ge;7.8** | 3.20E-4 | 0.000 | 0.000 | 0.000 | 0.000 | 3.20E-4 (0.03%) | 3.20E-4 (0.03%) | 2.70E-4 |",
        "| **M\u0026ge;7.9** | 1.90E-4 | 0.000 | 0.000 | 0.000 | 0.000 | 1.90E-4 (0.02%) | 1.90E-4 (0.02%) | 1.50E-4 |",
        "| **M\u0026ge;8** | 4.00E-5 | 0.000 | 0.000 | 0.000 | 0.000 | 4.00E-5 (0.00%) | 4.00E-5 (0.00%) | 3.00E-5 |",
        "| **M\u0026ge;8.1** | 0.000 | 0.000 | 0.000 | 0.000 | 0.000 | 0.000 (0.00%) | 0.000 (0.00%) | 0.000 |",
        "| **M\u0026ge;8.2** | 0.000 | 0.000 | 0.000 | 0.000 | 0.000 | 0.000 (0.00%) | 0.000 (0.00%) | 0.000 |",
        "| **M\u0026ge;8.3** | 0.000 | 0.000 | 0.000 | 0.000 | 0.000 | 0.000 (0.00%) | 0.000 (0.00%) | 0.000 |",
        "| **M\u0026ge;8.4** | 0.000 | 0.000 | 0.000 | 0.000 | 0.000 | 0.000 (0.00%) | 0.000 (0.00%) | 0.000 |",
        "| **M\u0026ge;8.5** | 0.000 | 0.000 | 0.000 | 0.000 | 0.000 | 0.000 (0.00%) | 0.000 (0.00%) | 0.000 |",
        "| **M\u0026ge;8.6** | 0.000 | 0.000 | 0.000 | 0.000 | 0.000 | 0.000 (0.00%) | 0.000 (0.00%) | 0.000 |",
        "| **M\u0026ge;8.7** | 0.000 | 0.000 | 0.000 | 0.000 | 0.000 | 0.000 (0.00%) | 0.000 (0.00%) | 0.000 |",
        "| **M\u0026ge;8.8** | 0.000 | 0.000 | 0.000 | 0.000 | 0.000 | 0.000 (0.00%) | 0.000 (0.00%) | 0.000 |",
        "| **M\u0026ge;8.9** | 0.000 | 0.000 | 0.000 | 0.000 | 0.000 | 0.000 (0.00%) | 0.000 (0.00%) | 0.000 |",
        "| **M\u0026ge;9** | 0.000 | 0.000 | 0.000 | 0.000 | 0.000 | 0.000 (0.00%) | 0.000 (0.00%) | 0.000 |",
        ""
      ]
    },
    {
      "className": "scratch.UCERF3.erf.ETAS.analysis.ETAS_HazardChangePlot",
      "version": 1,
      "time": 1565415282417,
      "markdown": [
        "## Hazard Change Over Time",
        "*[(top)](#table-of-contents)*",
        "",
        "These plots show how the probability of ruptures of various magnitudes within 100km of any scenario rupture changes over time",
        "",
        "### M\u0026ge;5.0 Hazard Change Over Time",
        "*[(top)](#table-of-contents)*",
        "",
        "![Hazard Change](plots/hazard_change_100km_m5.0.png)",
        "",
        "| Forecast Duration | UCERF3-ETAS [95% Conf] | UCERF3-ETAS Triggered Only | UCERF3-TD | UCERF3-ETAS/TD Gain | UCERF3-TI |",
        "|-----|-----|-----|-----|-----|-----|",
        "| 1 Hour | 0.773 [0.771 - 0.776] | 0.773 | 7.14E-5 | 10833.2 | 7.09E-5 |",
        "| 1 Day | 0.977 [0.976 - 0.978] | 0.977 | 1.71E-3 | 570.94 | 1.70E-3 |",
        "| 1 Week | 0.996 [0.995 - 0.996] | 0.996 | 0.012 | 83.53 | 0.012 |",
        "| 1 Month | 0.999 [0.998 - 0.999] | 0.999 | 0.050 | 19.94 | 0.050 |",
        "| 1 Year | 1.000 [1.000 - 1.000] | 1.000 | 0.465 | 2.15 | 0.463 |",
        "| 10 Years | 1.000 [1.000 - 1.000] | 1.000 | 0.998 | 1 | 0.998 |",
        "| 30 Years | 1.000 [1.000 - 1.000] \\* | \\* | 1.000 | 1 \\* | 1.000 |",
        "| 100 Years | 1.000 [1.000 - 1.000] \\* | \\* | 1.000 | 1 \\* | 1.000 |",
        "",
        "\\* *forecast duration is longer than simulation length, only ETAS ruptures from the first 10 years are included*",
        "### M\u0026ge;6.0 Hazard Change Over Time",
        "*[(top)](#table-of-contents)*",
        "",
        "![Hazard Change](plots/hazard_change_100km_m6.0.png)",
        "",
        "| Forecast Duration | UCERF3-ETAS [95% Conf] | UCERF3-ETAS Triggered Only | UCERF3-TD | UCERF3-ETAS/TD Gain | UCERF3-TI |",
        "|-----|-----|-----|-----|-----|-----|",
        "| 1 Hour | 0.110 [0.108 - 0.112] | 0.110 | 7.85E-6 | 14038.44 | 7.36E-6 |",
        "| 1 Day | 0.270 [0.268 - 0.273] | 0.270 | 1.88E-4 | 1434.67 | 1.77E-4 |",
        "| 1 Week | 0.375 [0.372 - 0.378] | 0.374 | 1.32E-3 | 284.13 | 1.23E-3 |",
        "| 1 Month | 0.449 [0.446 - 0.452] | 0.446 | 5.64E-3 | 79.58 | 5.28E-3 |",
        "| 1 Year | 0.586 [0.583 - 0.589] | 0.556 | 0.067 | 8.8 | 0.062 |",
        "| 10 Years | 0.819 [0.818 - 0.821] | 0.640 | 0.498 | 1.65 | 0.475 |",
        "| 30 Years | 0.955 [0.954 - 0.955] \\* | \\* | 0.874 | 1.09 \\* | 0.855 |",
        "| 100 Years | 1.000 [1.000 - 1.000] \\* | \\* | 0.999 | 1 \\* | 0.998 |",
        "",
        "\\* *forecast duration is longer than simulation length, only ETAS ruptures from the first 10 years are included*",
        "### M\u0026ge;7.0 Hazard Change Over Time",
        "*[(top)](#table-of-contents)*",
        "",
        "![Hazard Change](plots/hazard_change_100km_m7.0.png)",
        "",
        "| Forecast Duration | UCERF3-ETAS [95% Conf] | UCERF3-ETAS Triggered Only | UCERF3-TD | UCERF3-ETAS/TD Gain | UCERF3-TI |",
        "|-----|-----|-----|-----|-----|-----|",
        "| 1 Hour | 9.41E-3 [8.83E-3 - 0.010] | 9.41E-3 | 7.16E-7 | 13145.9 | 6.48E-7 |",
        "| 1 Day | 0.027 [0.026 - 0.028] | 0.027 | 1.72E-5 | 1577.75 | 1.55E-5 |",
        "| 1 Week | 0.041 [0.040 - 0.042] | 0.041 | 1.20E-4 | 339.81 | 1.09E-4 |",
        "| 1 Month | 0.053 [0.052 - 0.054] | 0.052 | 5.15E-4 | 102.75 | 4.66E-4 |",
        "| 1 Year | 0.081 [0.079 - 0.083] | 0.075 | 6.26E-3 | 12.93 | 5.66E-3 |",
        "| 10 Years | 0.153 [0.152 - 0.155] | 0.099 | 0.061 | 2.52 | 0.055 |",
        "| 30 Years | 0.255 [0.254 - 0.257] \\* | \\* | 0.174 | 1.47 \\* | 0.157 |",
        "| 100 Years | 0.535 [0.534 - 0.536] \\* | \\* | 0.485 | 1.1 \\* | 0.433 |",
        "",
        "\\* *forecast duration is longer than simulation length, only ETAS ruptures from the first 10 years are included*",
        "### M\u0026ge;8.0 Hazard Change Over Time",
        "*[(top)](#table-of-contents)*",
        "",
        "![Hazard Change](plots/hazard_change_100km_m8.0.png)",
        "",
        "| Forecast Duration | UCERF3-ETAS [95% Conf] | UCERF3-ETAS Triggered Only | UCERF3-TD | UCERF3-ETAS/TD Gain | UCERF3-TI |",
        "|-----|-----|-----|-----|-----|-----|",
        "| 1 Hour | 4.00E-5 [1.28E-5 - 1.10E-4] | 4.00E-5 | 1.24E-8 | 3235.63 | 1.06E-8 |",
        "| 1 Day | 1.30E-4 [7.26E-5 - 2.29E-4] | 1.30E-4 | 2.97E-7 | 439.02 | 2.54E-7 |",
        "| 1 Week | 2.52E-4 [1.67E-4 - 3.77E-4] | 2.50E-4 | 2.08E-6 | 121.34 | 1.78E-6 |",
        "| 1 Month | 3.29E-4 [2.31E-4 - 4.66E-4] | 3.20E-4 | 8.90E-6 | 36.94 | 7.63E-6 |",
        "| 1 Year | 6.68E-4 [5.35E-4 - 8.41E-4] | 5.60E-4 | 1.08E-4 | 6.17 | 9.29E-5 |",
        "| 10 Years | 1.88E-3 [1.72E-3 - 2.07E-3] | 7.80E-4 | 1.10E-3 | 1.71 | 9.29E-4 |",
        "| 30 Years | 4.28E-3 [4.12E-3 - 4.48E-3] \\* | \\* | 3.50E-3 | 1.22 \\* | 2.78E-3 |",
        "| 100 Years | 0.014 [0.014 - 0.015] \\* | \\* | 0.014 | 1.06 \\* | 9.25E-3 |",
        "",
        "\\* *forecast duration is longer than simulation length, only ETAS ruptures from the first 10 years are included*"
      ]
    },
    {
      "className": "scratch.UCERF3.erf.ETAS.analysis.ETAS_TriggerRuptureFaultDistancesPlot",
      "version": 1,
      "time": 1565415282417,
      "markdown": [
        "## Trigger Rupture Fault Map",
        "*[(top)](#table-of-contents)*",
        "",
        "![Map](plots/trigger_rup_fault_map.png)",
        "## Trigger Rupture Depth Map",
        "*[(top)](#table-of-contents)*",
        "",
        "![Map](plots/trigger_rup_depth_map.png)",
        "## Fault Distances To Triggers",
        "*[(top)](#table-of-contents)*",
        "",
        "| Section Name | Strike, Dip, Rake | # Hypos In Poly | Max Mag w/ Hypo In Poly | # Surfs In Poly | Max Mag w/ Surf In Poly | Min Dist To Any (km) | Min Poly Dist To Any (km) | Min Dist To Largest (km) | Min Poly Dist To Largest (km) | Min Hypo Dist To Largest (km) | Min Hypo Poly Dist To Largest (km) |",
        "|-----|-----|-----|-----|-----|-----|-----|-----|-----|-----|-----|-----|",
        "| Airport Lake | 359, 50, -90 | 90 | 7.1 | 90 | 7.1 | 0.036 | 0.000 | 0.036 | 0.000 | 5.612 | 0.000 |",
        "| Little Lake | 327, 90, 180 | 16 | 3.85 | 17 | 7.1 | 2.321 | 0.000 | 11.284 | 0.000 | 13.471 | 1.469 |",
        "| Garlock (Central) | 71, 90, 0 | 2 | 3.21 | 3 | 7.1 | 5.600 | 0.000 | 5.600 | 0.000 | 22.766 | 10.797 |",
        "| So Sierra Nevada | 2, 50, -90 | 1 | 2.75 | 1 | 2.75 | 1.410 | 0.000 | 4.248 | 4.233 | 16.191 | 15.188 |",
        "| Tank Canyon | 189, 50, -90 | 0 |  | 0 |  | 9.015 | 9.011 | 9.015 | 9.011 | 17.039 | 16.895 |",
        "| Blackwater | 323, 90, 180 | 0 |  | 0 |  | 14.394 | 8.726 | 14.394 | 8.726 | 29.622 | 27.613 |",
        "| Scodie Lineament | 221, 68, 0 | 0 |  | 0 |  | 16.722 | 15.781 | 28.750 | 27.702 | 36.559 | 32.668 |"
      ]
    },
    {
      "className": "scratch.UCERF3.erf.ETAS.analysis.ETAS_SimulatedCatalogPlot",
      "version": 1,
      "time": 1565415282417,
      "markdown": [
        "## Individual Simulated Catalog Maps",
        "*[(top)](#table-of-contents)*",
        "",
        "These are map plots of individual catalogs from the simulations, selected as the closest catalog to each of the given percentiles in terms of total number of events.",
        "",
        "| Duration | p0.0 %-ile | p25.0 %-ile | p50.0 %-ile | p75.0 %-ile | p90.0 %-ile | p95.0 %-ile | p97.5 %-ile | p98.0 %-ile | p99.0 %-ile | p99.5 %-ile | p99.9 %-ile | p100.0 %-ile |",
        "|-----|-----|-----|-----|-----|-----|-----|-----|-----|-----|-----|-----|-----|",
        "| **1 Week** | ![Map](plots/sim_catalog_map_p0.0_1wk.png) | ![Map](plots/sim_catalog_map_p25.0_1wk.png) | ![Map](plots/sim_catalog_map_p50.0_1wk.png) | ![Map](plots/sim_catalog_map_p75.0_1wk.png) | ![Map](plots/sim_catalog_map_p90.0_1wk.png) | ![Map](plots/sim_catalog_map_p95.0_1wk.png) | ![Map](plots/sim_catalog_map_p97.5_1wk.png) | ![Map](plots/sim_catalog_map_p98.0_1wk.png) | ![Map](plots/sim_catalog_map_p99.0_1wk.png) | ![Map](plots/sim_catalog_map_p99.5_1wk.png) | ![Map](plots/sim_catalog_map_p99.9_1wk.png) | ![Map](plots/sim_catalog_map_p100.0_1wk.png) |",
        "| **1 Month** | ![Map](plots/sim_catalog_map_p0.0_1mo.png) | ![Map](plots/sim_catalog_map_p25.0_1mo.png) | ![Map](plots/sim_catalog_map_p50.0_1mo.png) | ![Map](plots/sim_catalog_map_p75.0_1mo.png) | ![Map](plots/sim_catalog_map_p90.0_1mo.png) | ![Map](plots/sim_catalog_map_p95.0_1mo.png) | ![Map](plots/sim_catalog_map_p97.5_1mo.png) | ![Map](plots/sim_catalog_map_p98.0_1mo.png) | ![Map](plots/sim_catalog_map_p99.0_1mo.png) | ![Map](plots/sim_catalog_map_p99.5_1mo.png) | ![Map](plots/sim_catalog_map_p99.9_1mo.png) | ![Map](plots/sim_catalog_map_p100.0_1mo.png) |",
        "| **1 Year** | ![Map](plots/sim_catalog_map_p0.0_1yr.png) | ![Map](plots/sim_catalog_map_p25.0_1yr.png) | ![Map](plots/sim_catalog_map_p50.0_1yr.png) | ![Map](plots/sim_catalog_map_p75.0_1yr.png) | ![Map](plots/sim_catalog_map_p90.0_1yr.png) | ![Map](plots/sim_catalog_map_p95.0_1yr.png) | ![Map](plots/sim_catalog_map_p97.5_1yr.png) | ![Map](plots/sim_catalog_map_p98.0_1yr.png) | ![Map](plots/sim_catalog_map_p99.0_1yr.png) | ![Map](plots/sim_catalog_map_p99.5_1yr.png) | ![Map](plots/sim_catalog_map_p99.9_1yr.png) | ![Map](plots/sim_catalog_map_p100.0_1yr.png) |",
        "| **10 Year** | ![Map](plots/sim_catalog_map_p0.0_10yr.png) | ![Map](plots/sim_catalog_map_p25.0_10yr.png) | ![Map](plots/sim_catalog_map_p50.0_10yr.png) | ![Map](plots/sim_catalog_map_p75.0_10yr.png) | ![Map](plots/sim_catalog_map_p90.0_10yr.png) | ![Map](plots/sim_catalog_map_p95.0_10yr.png) | ![Map](plots/sim_catalog_map_p97.5_10yr.png) | ![Map](plots/sim_catalog_map_p98.0_10yr.png) | ![Map](plots/sim_catalog_map_p99.0_10yr.png) | ![Map](plots/sim_catalog_map_p99.5_10yr.png) | ![Map](plots/sim_catalog_map_p99.9_10yr.png) | ![Map](plots/sim_catalog_map_p100.0_10yr.png) |"
      ]
    },
    {
      "className": "scratch.UCERF3.erf.ETAS.analysis.ETAS_ComcatComparePlot",
      "version": 15,
      "time": 1570329196100,
      "markdown": [
        "## ComCat Data Comparisons",
        "*[(top)](#table-of-contents)*",
        "",
        "These plots compare simulated sequences with data from ComCat. All plots only consider events with hypocenters inside the ComCat region defined in the JSON input file.",
        "",
        "Last updated at 2019/10/06 02:33:41 UTC, 3 mo after the simulation start time",
        "",
        "### ComCat Magnitude-Number Distributions",
        "*[(top)](#table-of-contents)*",
        "",
        "| Incremental MND | Cumulative MND |",
        "|-----|-----|",
        "| ![Incremental MND](plots/comcat_compare_mag_num.png) | ![Cumi MND](plots/comcat_compare_mag_num_cumulative.png) |",
        "",
        "### ComCat Time-Dependent Mc",
        "*[(top)](#table-of-contents)*",
        "",
        "The following plots compare simulation results with ComCat data above a magnitude threshold. Plots labeled as *M\u0026ge;Mc(t)* use the time-dependent magnitude of completeness (Mc) defined in Helmstetter et al. (2006), which is plotted below. In the case of multiple M\u0026ge5 ruptures, either as input to the simulation or in the comparison data, the maximum calculated time-dependent Mc is used. This time-dependent Mc function is plotted below.",
        "",
        "![TD MC](plots/comcat_compare_td_mc.png)",
        "",
        "### ComCat Cumulative Number Vs Time",
        "*[(top)](#table-of-contents)*",
        "",
        "| M\u0026ge;Mc(t) | M\u0026ge;3.5 | M\u0026ge;4 | M\u0026ge;5 | M\u0026ge;6 | M\u0026ge;7 |",
        "|-----|-----|-----|-----|-----|-----|",
        "| ![MND](plots/comcat_compare_cumulative_num_td_mc.png) | ![MND](plots/comcat_compare_cumulative_num_m3.5.png) | ![MND](plots/comcat_compare_cumulative_num_m4.png) | ![MND](plots/comcat_compare_cumulative_num_m5.png) | ![MND](plots/comcat_compare_cumulative_num_m6.png) | ![MND](plots/comcat_compare_cumulative_num_m7.png) |",
        "",
        "### ComCat Cumulative Number Simulation Percentiles",
        "*[(top)](#table-of-contents)*",
        "",
        "![MND](plots/comcat_compare_cumulative_num_percentile.png)",
        "",
        "### ComCat Probability Spatial Distribution",
        "*[(top)](#table-of-contents)*",
        "",
        "|  | 1 Day | 1 Week | 1 Month | Current (3 Month) |",
        "|-----|-----|-----|-----|-----|",
        "| **M\u0026ge;Mc(t)** | ![Map](plots/comcat_compare_prob_1d_td_mc.png) | ![Map](plots/comcat_compare_prob_1wk_td_mc.png) | ![Map](plots/comcat_compare_prob_1mo_td_mc.png) | ![Map](plots/comcat_compare_prob_current_td_mc.png) |",
        "| **M\u0026ge;3.5** | ![Map](plots/comcat_compare_prob_1d_m3.5.png) | ![Map](plots/comcat_compare_prob_1wk_m3.5.png) | ![Map](plots/comcat_compare_prob_1mo_m3.5.png) | ![Map](plots/comcat_compare_prob_current_m3.5.png) |",
        "| **M\u0026ge;4** | ![Map](plots/comcat_compare_prob_1d_m4.png) | ![Map](plots/comcat_compare_prob_1wk_m4.png) | ![Map](plots/comcat_compare_prob_1mo_m4.png) | ![Map](plots/comcat_compare_prob_current_m4.png) |",
        "| **M\u0026ge;5** | ![Map](plots/comcat_compare_prob_1d_m5.png) | ![Map](plots/comcat_compare_prob_1wk_m5.png) | ![Map](plots/comcat_compare_prob_1mo_m5.png) | ![Map](plots/comcat_compare_prob_current_m5.png) |",
        "| **M\u0026ge;6** | ![Map](plots/comcat_compare_prob_1d_m6.png) | ![Map](plots/comcat_compare_prob_1wk_m6.png) | ![Map](plots/comcat_compare_prob_1mo_m6.png) | ![Map](plots/comcat_compare_prob_current_m6.png) |",
        "| **M\u0026ge;7** | ![Map](plots/comcat_compare_prob_1d_m7.png) | ![Map](plots/comcat_compare_prob_1wk_m7.png) | ![Map](plots/comcat_compare_prob_1mo_m7.png) | ![Map](plots/comcat_compare_prob_current_m7.png) |",
        "| **M\u0026ge;8** | ![Map](plots/comcat_compare_prob_1d_m8.png) | ![Map](plots/comcat_compare_prob_1wk_m8.png) | ![Map](plots/comcat_compare_prob_1mo_m8.png) | ![Map](plots/comcat_compare_prob_current_m8.png) |",
        "",
        "### ComCat Mean Expectation Spatial Distribution",
        "*[(top)](#table-of-contents)*",
        "",
        "|  | 1 Day | 1 Week | 1 Month | Current (3 Month) |",
        "|-----|-----|-----|-----|-----|",
        "| **M\u0026ge;Mc(t)** | ![Map](plots/comcat_compare_mean_1d_td_mc.png) | ![Map](plots/comcat_compare_mean_1wk_td_mc.png) | ![Map](plots/comcat_compare_mean_1mo_td_mc.png) | ![Map](plots/comcat_compare_mean_current_td_mc.png) |",
        "| **M\u0026ge;3.5** | ![Map](plots/comcat_compare_mean_1d_m3.5.png) | ![Map](plots/comcat_compare_mean_1wk_m3.5.png) | ![Map](plots/comcat_compare_mean_1mo_m3.5.png) | ![Map](plots/comcat_compare_mean_current_m3.5.png) |",
        "| **M\u0026ge;4** | ![Map](plots/comcat_compare_mean_1d_m4.png) | ![Map](plots/comcat_compare_mean_1wk_m4.png) | ![Map](plots/comcat_compare_mean_1mo_m4.png) | ![Map](plots/comcat_compare_mean_current_m4.png) |",
        "| **M\u0026ge;5** | ![Map](plots/comcat_compare_mean_1d_m5.png) | ![Map](plots/comcat_compare_mean_1wk_m5.png) | ![Map](plots/comcat_compare_mean_1mo_m5.png) | ![Map](plots/comcat_compare_mean_current_m5.png) |",
        "| **M\u0026ge;6** | ![Map](plots/comcat_compare_mean_1d_m6.png) | ![Map](plots/comcat_compare_mean_1wk_m6.png) | ![Map](plots/comcat_compare_mean_1mo_m6.png) | ![Map](plots/comcat_compare_mean_current_m6.png) |",
        "| **M\u0026ge;7** | ![Map](plots/comcat_compare_mean_1d_m7.png) | ![Map](plots/comcat_compare_mean_1wk_m7.png) | ![Map](plots/comcat_compare_mean_1mo_m7.png) | ![Map](plots/comcat_compare_mean_current_m7.png) |",
        "| **M\u0026ge;8** | ![Map](plots/comcat_compare_mean_1d_m8.png) | ![Map](plots/comcat_compare_mean_1wk_m8.png) | ![Map](plots/comcat_compare_mean_1mo_m8.png) | ![Map](plots/comcat_compare_mean_current_m8.png) |",
        "",
        "### ComCat Depth Distribution",
        "*[(top)](#table-of-contents)*",
        "",
        "| M\u0026ge;Mc(t) | M\u0026ge;3.5 | M\u0026ge;4 | M\u0026ge;5 | M\u0026ge;6 | M\u0026ge;7 | M\u0026ge;8 |",
        "|-----|-----|-----|-----|-----|-----|-----|",
        "| ![Depth Distribution](plots/comcat_compare_depth_td_mc.png) | ![Depth Distribution](plots/comcat_compare_depth_m3.5.png) | ![Depth Distribution](plots/comcat_compare_depth_m4.png) | ![Depth Distribution](plots/comcat_compare_depth_m5.png) | ![Depth Distribution](plots/comcat_compare_depth_m6.png) | ![Depth Distribution](plots/comcat_compare_depth_m7.png) | ![Depth Distribution](plots/comcat_compare_depth_m8.png) |"
      ]
    },
    {
      "className": "scratch.UCERF3.erf.ETAS.analysis.ETAS_FaultParticipationPlot",
      "version": 1,
      "time": 1565415282417,
      "markdown": [
        "## Section Participation",
        "*[(top)](#table-of-contents)*",
        "",
        "### Section Participation Plots",
        "*[(top)](#table-of-contents)*",
        "",
        "| Min Mag | 1 yr Triggered Ruptures (no spontaneous) | 10 yr Triggered Ruptures (no spontaneous) | 10 yr Triggered Ruptures (primary aftershocks only) |",
        "|-----|-----|-----|-----|",
        "| **All Supra. Seis.** | ![Participation Plot](plots/fault_participation_partic_1yr_triggered.png) | ![Participation Plot](plots/fault_participation_partic_10yr_triggered.png) | ![Participation Plot](plots/fault_participation_partic_10yr_triggered_primary.png) |",
        "| **M\u0026ge;6.5** | ![Participation Plot](plots/fault_participation_partic_1yr_m6.5_triggered.png) | ![Participation Plot](plots/fault_participation_partic_10yr_m6.5_triggered.png) | ![Participation Plot](plots/fault_participation_partic_10yr_m6.5_triggered_primary.png) |",
        "| **M\u0026ge;7** | ![Participation Plot](plots/fault_participation_partic_1yr_m7.0_triggered.png) | ![Participation Plot](plots/fault_participation_partic_10yr_m7.0_triggered.png) | ![Participation Plot](plots/fault_participation_partic_10yr_m7.0_triggered_primary.png) |",
        "| **M\u0026ge;7.5** | ![Participation Plot](plots/fault_participation_partic_1yr_m7.5_triggered.png) | ![Participation Plot](plots/fault_participation_partic_10yr_m7.5_triggered.png) | ![Participation Plot](plots/fault_participation_partic_10yr_m7.5_triggered_primary.png) |",
        "| **M\u0026ge;8** | ![Participation Plot](plots/fault_participation_partic_1yr_m8.0_triggered.png) | ![Participation Plot](plots/fault_participation_partic_10yr_m8.0_triggered.png) | ![Participation Plot](plots/fault_participation_partic_10yr_m8.0_triggered_primary.png) |",
        "",
        "### Supra-Seismogenic Parent Sections Table",
        "*[(top)](#table-of-contents)*",
        "",
        "*First 10 of 239 with matching ruptures shown*",
        "",
        "| Parent Name | Triggered 10 Year Mean Count | Triggered 1 Day Prob | Triggered 1 Week Prob | Triggered 1 Month Prob | Triggered 1 Year Prob | Triggered 10 Year Prob | Triggered 10 Year Primary Mean Count |",
        "|-----|-----|-----|-----|-----|-----|-----|-----|",
        "| Garlock (Central) | 0.18555 | 0.05074 | 0.07364 | 0.09288 | 0.12855 | 0.16215 | 0.07871 |",
        "| Tank Canyon | 0.1829 | 0.02595 | 0.04198 | 0.05651 | 0.08775 | 0.12131 | 0.03179 |",
        "| Little Lake | 0.07824 | 0.0235 | 0.0348 | 0.04365 | 0.05989 | 0.07503 | 0.0381 |",
        "| Owl Lake | 0.07111 | 0.01116 | 0.0183 | 0.02539 | 0.04029 | 0.05577 | 0.01198 |",
        "| Airport Lake | 0.06139 | 0.02121 | 0.03048 | 0.03752 | 0.04952 | 0.06084 | 0.03565 |",
        "| Panamint Valley | 0.05867 | 0.01034 | 0.01699 | 0.02301 | 0.03616 | 0.05171 | 0.01313 |",
        "| Garlock (East) | 0.0489 | 0.00705 | 0.01195 | 0.01669 | 0.02716 | 0.03913 | 0.00825 |",
        "| Hunter Mountain-Saline Valley | 0.02788 | 0.00599 | 0.00927 | 0.01217 | 0.01829 | 0.02585 | 0.00796 |",
        "| Ash Hill | 0.02171 | 0.00251 | 0.00444 | 0.00675 | 0.01152 | 0.01857 | 0.00168 |",
        "| Blackwater | 0.01744 | 0.00225 | 0.004 | 0.0058 | 0.00981 | 0.0152 | 0.00302 |",
        "",
        "### M6.5 Parent Sections Table",
        "*[(top)](#table-of-contents)*",
        "",
        "*First 10 of 208 with matching ruptures shown*",
        "",
        "| Parent Name | Triggered 10 Year Mean Count | Triggered 1 Day Prob | Triggered 1 Week Prob | Triggered 1 Month Prob | Triggered 1 Year Prob | Triggered 10 Year Prob | Triggered 10 Year Primary Mean Count |",
        "|-----|-----|-----|-----|-----|-----|-----|-----|",
        "| Garlock (Central) | 0.08857 | 0.02261 | 0.03385 | 0.04345 | 0.06207 | 0.0816 | 0.03388 |",
        "| Panamint Valley | 0.05461 | 0.00974 | 0.01606 | 0.02173 | 0.03395 | 0.04843 | 0.01286 |",
        "| Little Lake | 0.04636 | 0.01483 | 0.02154 | 0.027 | 0.03637 | 0.04524 | 0.0242 |",
        "| Airport Lake | 0.04594 | 0.01605 | 0.02299 | 0.0284 | 0.03731 | 0.04575 | 0.0268 |",
        "| Owl Lake | 0.03875 | 0.00854 | 0.01322 | 0.01795 | 0.0278 | 0.03788 | 0.01081 |",
        "| Garlock (East) | 0.03218 | 0.00559 | 0.00907 | 0.01248 | 0.0197 | 0.02761 | 0.00779 |",
        "| Tank Canyon | 0.03128 | 0.00391 | 0.00736 | 0.01109 | 0.01981 | 0.03037 | 0.0032 |",
        "| Hunter Mountain-Saline Valley | 0.02718 | 0.00591 | 0.00919 | 0.01207 | 0.0181 | 0.02556 | 0.00789 |",
        "| Garlock (West) | 0.01488 | 0.00369 | 0.00576 | 0.00745 | 0.0109 | 0.0148 | 0.00534 |",
        "| Death Valley (So) | 0.00918 | 8.4E-4 | 0.00171 | 0.00257 | 0.00513 | 0.00839 | 2.5E-4 |",
        "",
        "### M7 Parent Sections Table",
        "*[(top)](#table-of-contents)*",
        "",
        "*First 10 of 165 with matching ruptures shown*",
        "",
        "| Parent Name | Triggered 10 Year Mean Count | Triggered 1 Day Prob | Triggered 1 Week Prob | Triggered 1 Month Prob | Triggered 1 Year Prob | Triggered 10 Year Prob | Triggered 10 Year Primary Mean Count |",
        "|-----|-----|-----|-----|-----|-----|-----|-----|",
        "| Garlock (Central) | 0.07922 | 0.02023 | 0.03033 | 0.03919 | 0.05612 | 0.07389 | 0.03019 |",
        "| Panamint Valley | 0.03599 | 0.00791 | 0.01251 | 0.01656 | 0.0248 | 0.03482 | 0.01107 |",
        "| Hunter Mountain-Saline Valley | 0.02597 | 0.00583 | 0.00907 | 0.01193 | 0.01788 | 0.02525 | 0.00778 |",
        "| Owl Lake | 0.02539 | 0.00728 | 0.01063 | 0.0137 | 0.01966 | 0.02536 | 0.01055 |",
        "| Garlock (East) | 0.02099 | 0.00488 | 0.00763 | 0.01015 | 0.01518 | 0.0205 | 0.0075 |",
        "| Garlock (West) | 0.01471 | 0.00368 | 0.00574 | 0.0074 | 0.01083 | 0.01465 | 0.00533 |",
        "| Little Lake | 0.01021 | 0.00342 | 0.00505 | 0.00615 | 0.00819 | 0.01018 | 0.00573 |",
        "| Airport Lake | 0.00961 | 0.00324 | 0.00481 | 0.00583 | 0.00777 | 0.00961 | 0.00552 |",
        "| San Andreas (Mojave N) | 0.00763 | 0.00162 | 0.00251 | 0.00323 | 0.00496 | 0.00683 | 0.00223 |",
        "| San Andreas (Mojave S) | 0.00617 | 0.00132 | 0.00201 | 0.00261 | 0.00406 | 0.00568 | 0.00177 |",
        "",
        "### M7.5 Parent Sections Table",
        "*[(top)](#table-of-contents)*",
        "",
        "*First 10 of 104 with matching ruptures shown*",
        "",
        "| Parent Name | Triggered 10 Year Mean Count | Triggered 1 Day Prob | Triggered 1 Week Prob | Triggered 1 Month Prob | Triggered 1 Year Prob | Triggered 10 Year Prob | Triggered 10 Year Primary Mean Count |",
        "|-----|-----|-----|-----|-----|-----|-----|-----|",
        "| Garlock (Central) | 0.03537 | 0.00876 | 0.01334 | 0.01727 | 0.02503 | 0.03409 | 0.01227 |",
        "| Panamint Valley | 0.02446 | 0.00578 | 0.00897 | 0.01176 | 0.01747 | 0.02443 | 0.00771 |",
        "| Hunter Mountain-Saline Valley | 0.02442 | 0.00577 | 0.00896 | 0.01174 | 0.01744 | 0.02439 | 0.00771 |",
        "| Garlock (West) | 0.01332 | 0.00334 | 0.00513 | 0.00664 | 0.00978 | 0.01328 | 0.0048 |",
        "| Garlock (East) | 0.00817 | 0.00196 | 0.00309 | 0.00407 | 0.00611 | 0.00816 | 0.00311 |",
        "| San Andreas (Mojave N) | 0.00753 | 0.00161 | 0.0025 | 0.00322 | 0.00492 | 0.00678 | 0.00223 |",
        "| San Andreas (Mojave S) | 0.00589 | 0.0013 | 0.00197 | 0.00255 | 0.00396 | 0.00554 | 0.00174 |",
        "| San Andreas (San Bernardino N) | 0.00404 | 7.7E-4 | 0.00132 | 0.00171 | 0.00275 | 0.00392 | 0.0011 |",
        "| Owl Lake | 0.00245 | 6.3E-4 | 9.2E-4 | 0.00121 | 0.00173 | 0.00245 | 8.3E-4 |",
        "| San Andreas (San Bernardino S) | 0.00194 | 4.6E-4 | 7.1E-4 | 8.6E-4 | 0.00137 | 0.00192 | 5.7E-4 |",
        "",
        "### M8 Parent Sections Table",
        "*[(top)](#table-of-contents)*",
        "",
        "*First 10 of 33 with matching ruptures shown*",
        "",
        "| Parent Name | Triggered 10 Year Mean Count | Triggered 1 Day Prob | Triggered 1 Week Prob | Triggered 1 Month Prob | Triggered 1 Year Prob | Triggered 10 Year Prob | Triggered 10 Year Primary Mean Count |",
        "|-----|-----|-----|-----|-----|-----|-----|-----|",
        "| San Andreas (Mojave N) | 0.00101 | 1.6E-4 | 2.9E-4 | 4.0E-4 | 7.0E-4 | 0.001 | 2.7E-4 |",
        "| San Andreas (Mojave S) | 0.00101 | 1.6E-4 | 2.9E-4 | 4.0E-4 | 7.0E-4 | 0.001 | 2.7E-4 |",
        "| San Andreas (San Bernardino N) | 0.00101 | 1.6E-4 | 2.9E-4 | 4.0E-4 | 7.0E-4 | 0.001 | 2.7E-4 |",
        "| Garlock (Central) | 7.8E-4 | 1.3E-4 | 2.5E-4 | 3.2E-4 | 5.6E-4 | 7.8E-4 | 2.6E-4 |",
        "| Garlock (West) | 7.8E-4 | 1.3E-4 | 2.5E-4 | 3.2E-4 | 5.6E-4 | 7.8E-4 | 2.6E-4 |",
        "| Garlock (East) | 5.7E-4 | 1.2E-4 | 2.2E-4 | 2.6E-4 | 4.2E-4 | 5.7E-4 | 2.3E-4 |",
        "| San Andreas (San Bernardino S) | 5.7E-4 | 1.1E-4 | 1.8E-4 | 2.1E-4 | 4.0E-4 | 5.7E-4 | 1.7E-4 |",
        "| San Andreas (San Gorgonio Pass-Garnet HIll) | 5.3E-4 | 1.0E-4 | 1.7E-4 | 1.9E-4 | 3.8E-4 | 5.3E-4 | 1.7E-4 |",
        "| San Andreas (Coachella) rev | 4.6E-4 | 7.0E-5 | 1.4E-4 | 1.6E-4 | 3.2E-4 | 4.6E-4 | 1.3E-4 |",
        "| San Jacinto (San Bernardino) | 3.3E-4 | 4.0E-5 | 8.0E-5 | 1.5E-4 | 2.4E-4 | 3.3E-4 | 8.0E-5 |",
        "",
        "### Fault Magnitude-Probability Distributions",
        "*[(top)](#table-of-contents)*",
        "",
        "The first 5 sections (sorted by trigger rate) are plotted below. All fault MPDs are available [here](plots/parent_sect_mpds/README.md)",
        "",
        "| 1 Week | 1 Month | 1 Year | 10 Year |",
        "|-----|-----|-----|-----|",
        "| ![MPD](plots/parent_sect_mpds/Garlock_Central_1wk.png) | ![MPD](plots/parent_sect_mpds/Garlock_Central_1mo.png) | ![MPD](plots/parent_sect_mpds/Garlock_Central_1yr.png) | ![MPD](plots/parent_sect_mpds/Garlock_Central_10yr.png) |",
        "| ![MPD](plots/parent_sect_mpds/Tank_Canyon_1wk.png) | ![MPD](plots/parent_sect_mpds/Tank_Canyon_1mo.png) | ![MPD](plots/parent_sect_mpds/Tank_Canyon_1yr.png) | ![MPD](plots/parent_sect_mpds/Tank_Canyon_10yr.png) |",
        "| ![MPD](plots/parent_sect_mpds/Little_Lake_1wk.png) | ![MPD](plots/parent_sect_mpds/Little_Lake_1mo.png) | ![MPD](plots/parent_sect_mpds/Little_Lake_1yr.png) | ![MPD](plots/parent_sect_mpds/Little_Lake_10yr.png) |",
        "| ![MPD](plots/parent_sect_mpds/Owl_Lake_1wk.png) | ![MPD](plots/parent_sect_mpds/Owl_Lake_1mo.png) | ![MPD](plots/parent_sect_mpds/Owl_Lake_1yr.png) | ![MPD](plots/parent_sect_mpds/Owl_Lake_10yr.png) |",
        "| ![MPD](plots/parent_sect_mpds/Airport_Lake_1wk.png) | ![MPD](plots/parent_sect_mpds/Airport_Lake_1mo.png) | ![MPD](plots/parent_sect_mpds/Airport_Lake_1yr.png) | ![MPD](plots/parent_sect_mpds/Airport_Lake_10yr.png) |"
      ]
    },
    {
      "className": "scratch.UCERF3.erf.ETAS.analysis.ETAS_GriddedNucleationPlot",
      "version": 1,
      "time": 1565415282417,
      "markdown": [
        "## Gridded Nucleation",
        "*[(top)](#table-of-contents)*",
        "",
        "| Min Mag | Triggered Ruptures (no spontaneous) | Triggered Ruptures (primary aftershocks only) |",
        "|-----|-----|-----|",
        "| **M\u0026ge;2.5** | ![Nucleation Plot](plots/gridded_nucleation_triggered_m2.5.png) | ![Nucleation Plot](plots/gridded_nucleation_triggered_primary_m2.5.png) |",
        "| **M\u0026ge;5** | ![Nucleation Plot](plots/gridded_nucleation_triggered_m5.0.png) | ![Nucleation Plot](plots/gridded_nucleation_triggered_primary_m5.0.png) |",
        "| **M\u0026ge;6** | ![Nucleation Plot](plots/gridded_nucleation_triggered_m6.0.png) | ![Nucleation Plot](plots/gridded_nucleation_triggered_primary_m6.0.png) |",
        "| **M\u0026ge;7** | ![Nucleation Plot](plots/gridded_nucleation_triggered_m7.0.png) | ![Nucleation Plot](plots/gridded_nucleation_triggered_primary_m7.0.png) |"
      ]
    }
  ]
}
