{
  "plotStartTime": 1571259051411,
  "plotEndTime": 1571259076930,
  "simulationsProcessed": 1000,
  "dataFile": {
    "path": "/home/scec-02/kmilner/ucerf3/etas_sim/2019_09_01-Start1919_100yr_ScaleFactor1p212_Spontaneous_HistoricalCatalog-includeSpont-histCatalog-full_td-scale1.212/results_m5_preserve_chain.bin"
  },
  "launcherGitHash": "3347936ff83c07695414d6ffe804046b1ed5195c",
  "launcherGitTime": 1571254385000,
  "plots": [
    {
      "className": "scratch.UCERF3.erf.ETAS.analysis.ETAS_MFD_Plot",
      "version": 2,
      "time": 1567403276738,
      "markdown": [
        "## Magnitude Frequency Distribution",
        "*[(top)](#table-of-contents)*",
        "",
        "**Legend**",
        "* **Mean** (thick black line): mean annual rate across all 1000 catalogs",
        "* **2.5%,97.5%** (thin black lines): annual rate percentiles across all 1000 catalogs",
        "* **Median** (thin blue line): median annual rate across all 1000 catalogs",
        "* **Mode** (thin cyan line): modal annual rate across all 1000 catalogs (scaled to annualized value)",
        "* **100 yr Probability** (thin red line): 100 year probability calculated as the fraction of catalogs with at least 1 occurrence",
        "* **100 yr Supraseismogenic Probability** (thin dashed red line): same as above, but only for supraseismogenic ruptures on explicitly modeled UCERF3 faults",
        "* **95% Conf** (light red shaded region): binomial 95% confidence bounds on probability",
        "",
        "![MFD Plot](plots/mfd.png)",
        "",
        "| Mag | Mean | 2.5 %ile | 97.5 %ile | Median | Mode | 100 yr Probability | 100 yr Supra-Seis Prob |",
        "|-----|-----|-----|-----|-----|-----|-----|-----|",
        "| **M\u0026ge;5** | 7.842 | 6.490 | 9.660 | 7.780 | 7.550 | 1.000 (100.00%) | 1.000 (100.00%) |",
        "| **M\u0026ge;5.1** | 6.206 | 5.090 | 7.710 | 6.160 | 5.970 | 1.000 (100.00%) | 1.000 (100.00%) |",
        "| **M\u0026ge;5.2** | 4.907 | 3.990 | 6.130 | 4.870 | 4.880 | 1.000 (100.00%) | 1.000 (100.00%) |",
        "| **M\u0026ge;5.3** | 3.871 | 3.130 | 4.850 | 3.840 | 3.720 | 1.000 (100.00%) | 1.000 (100.00%) |",
        "| **M\u0026ge;5.4** | 3.058 | 2.430 | 3.820 | 3.030 | 3.040 | 1.000 (100.00%) | 1.000 (100.00%) |",
        "| **M\u0026ge;5.5** | 2.407 | 1.890 | 3.040 | 2.380 | 2.310 | 1.000 (100.00%) | 1.000 (100.00%) |",
        "| **M\u0026ge;5.6** | 1.891 | 1.470 | 2.410 | 1.870 | 1.870 | 1.000 (100.00%) | 1.000 (100.00%) |",
        "| **M\u0026ge;5.7** | 1.476 | 1.120 | 1.900 | 1.460 | 1.510 | 1.000 (100.00%) | 1.000 (100.00%) |",
        "| **M\u0026ge;5.8** | 1.151 | 0.850 | 1.490 | 1.140 | 1.090 | 1.000 (100.00%) | 1.000 (100.00%) |",
        "| **M\u0026ge;5.9** | 0.881 | 0.630 | 1.160 | 0.880 | 0.890 | 1.000 (100.00%) | 1.000 (100.00%) |",
        "| **M\u0026ge;6** | 0.697 | 0.490 | 0.930 | 0.690 | 0.680 | 1.000 (100.00%) | 1.000 (100.00%) |",
        "| **M\u0026ge;6.1** | 0.535 | 0.360 | 0.720 | 0.530 | 0.520 | 1.000 (100.00%) | 1.000 (100.00%) |",
        "| **M\u0026ge;6.2** | 0.420 | 0.270 | 0.580 | 0.420 | 0.420 | 1.000 (100.00%) | 1.000 (100.00%) |",
        "| **M\u0026ge;6.3** | 0.326 | 0.200 | 0.470 | 0.320 | 0.310 | 1.000 (100.00%) | 1.000 (100.00%) |",
        "| **M\u0026ge;6.4** | 0.249 | 0.140 | 0.370 | 0.240 | 0.240 | 1.000 (100.00%) | 1.000 (100.00%) |",
        "| **M\u0026ge;6.5** | 0.189 | 0.090 | 0.300 | 0.190 | 0.210 | 1.000 (100.00%) | 1.000 (100.00%) |",
        "| **M\u0026ge;6.6** | 0.144 | 0.070 | 0.230 | 0.140 | 0.150 | 1.000 (100.00%) | 1.000 (100.00%) |",
        "| **M\u0026ge;6.7** | 0.106 | 0.050 | 0.180 | 0.100 | 0.110 | 1.000 (100.00%) | 0.998 (99.80%) |",
        "| **M\u0026ge;6.8** | 0.080 | 0.030 | 0.150 | 0.080 | 0.060 | 1.000 (100.00%) | 0.997 (99.70%) |",
        "| **M\u0026ge;6.9** | 0.060 | 0.020 | 0.120 | 0.060 | 0.060 | 0.997 (99.70%) | 0.994 (99.40%) |",
        "| **M\u0026ge;7** | 0.044 | 0.010 | 0.090 | 0.040 | 0.030 | 0.989 (98.90%) | 0.977 (97.70%) |",
        "| **M\u0026ge;7.1** | 0.033 | 0.000 | 0.070 | 0.030 | 0.030 | 0.966 (96.60%) | 0.948 (94.80%) |",
        "| **M\u0026ge;7.2** | 0.022 | 0.000 | 0.050 | 0.020 | 0.020 | 0.908 (90.80%) | 0.882 (88.20%) |",
        "| **M\u0026ge;7.3** | 0.017 | 0.000 | 0.050 | 0.020 | 0.010 | 0.843 (84.30%) | 0.824 (82.40%) |",
        "| **M\u0026ge;7.4** | 0.011 | 0.000 | 0.040 | 0.010 | 0.010 | 0.688 (68.80%) | 0.674 (67.40%) |",
        "| **M\u0026ge;7.5** | 7.35E-3 | 0.000 | 0.030 | 0.010 | 0.000 | 0.518 (51.80%) | 0.514 (51.40%) |",
        "| **M\u0026ge;7.6** | 4.22E-3 | 0.000 | 0.020 | 0.000 | 0.000 | 0.343 (34.30%) | 0.339 (33.90%) |",
        "| **M\u0026ge;7.7** | 2.25E-3 | 0.000 | 0.010 | 0.000 | 0.000 | 0.200 (20.00%) | 0.197 (19.70%) |",
        "| **M\u0026ge;7.8** | 1.20E-3 | 0.000 | 0.010 | 0.000 | 0.000 | 0.114 (11.40%) | 0.112 (11.20%) |",
        "| **M\u0026ge;7.9** | 6.00E-4 | 0.000 | 0.010 | 0.000 | 0.000 | 0.059 (5.90%) | 0.059 (5.90%) |",
        "| **M\u0026ge;8** | 3.30E-4 | 0.000 | 0.010 | 0.000 | 0.000 | 0.033 (3.30%) | 0.033 (3.30%) |",
        "| **M\u0026ge;8.1** | 1.30E-4 | 0.000 | 0.000 | 0.000 | 0.000 | 0.013 (1.30%) | 0.013 (1.30%) |",
        "| **M\u0026ge;8.2** | 1.00E-5 | 0.000 | 0.000 | 0.000 | 0.000 | 1.00E-3 (0.10%) | 1.00E-3 (0.10%) |",
        "| **M\u0026ge;8.3** | 0.000 | 0.000 | 0.000 | 0.000 | 0.000 | 0.000 (0.00%) | 0.000 (0.00%) |",
        "| **M\u0026ge;8.4** | 0.000 | 0.000 | 0.000 | 0.000 | 0.000 | 0.000 (0.00%) | 0.000 (0.00%) |",
        "| **M\u0026ge;8.5** | 0.000 | 0.000 | 0.000 | 0.000 | 0.000 | 0.000 (0.00%) | 0.000 (0.00%) |",
        "| **M\u0026ge;8.6** | 0.000 | 0.000 | 0.000 | 0.000 | 0.000 | 0.000 (0.00%) | 0.000 (0.00%) |",
        "| **M\u0026ge;8.7** | 0.000 | 0.000 | 0.000 | 0.000 | 0.000 | 0.000 (0.00%) | 0.000 (0.00%) |",
        "| **M\u0026ge;8.8** | 0.000 | 0.000 | 0.000 | 0.000 | 0.000 | 0.000 (0.00%) | 0.000 (0.00%) |",
        "| **M\u0026ge;8.9** | 0.000 | 0.000 | 0.000 | 0.000 | 0.000 | 0.000 (0.00%) | 0.000 (0.00%) |",
        "| **M\u0026ge;9** | 0.000 | 0.000 | 0.000 | 0.000 | 0.000 | 0.000 (0.00%) | 0.000 (0.00%) |",
        ""
      ]
    },
    {
      "className": "scratch.UCERF3.erf.ETAS.analysis.ETAS_LongTermRateVariabilityPlot",
      "version": 1,
      "time": 1567403276738,
      "markdown": [
        "## Long Term Rate Variability",
        "*[(top)](#table-of-contents)*",
        "",
        "### 80 Year Variability",
        "*[(top)](#table-of-contents)*",
        "",
        "![Fixed Time Plot](plots/long_term_var_80yr.png)",
        "",
        "[Download CSV Here](plots/long_term_var_80yr.csv)",
        "",
        "| **Magnitude** | Mean | Median | Mode | Std. Dev. | 2.5 %-ile | 16 %-ile | 84 %-ile | 97.5 %-ile |",
        "|-----|-----|-----|-----|-----|-----|-----|-----|-----|",
        "| **5.0** | 7.8577623 | 7.7625 | 7.825 | 0.87604946 | 6.375 | 7.0125 | 8.725 | 9.925 |",
        "| **5.1** | 6.2182875 | 6.15 | 5.8125 | 0.71615803 | 5.025 | 5.5125 | 6.9 | 7.8625 |",
        "| **5.2** | 4.917775 | 4.85 | 4.875 | 0.5820134 | 3.9625 | 4.3375 | 5.5125 | 6.225 |",
        "| **5.3** | 3.8784125 | 3.8125 | 3.7125 | 0.477344 | 3.0875 | 3.4 | 4.375 | 4.95 |",
        "| **5.4** | 3.0635624 | 3.025 | 3.05 | 0.3926876 | 2.3375 | 2.6875 | 3.45 | 3.925 |",
        "| **5.5** | 2.4130375 | 2.3875 | 2.35 | 0.3193068 | 1.8375 | 2.1 | 2.75 | 3.1125 |",
        "| **5.6** | 1.896475 | 1.875 | 1.85 | 0.26322278 | 1.45 | 1.6375 | 2.1625 | 2.475 |",
        "| **5.7** | 1.4808375 | 1.4625 | 1.3875 | 0.21791442 | 1.1 | 1.2625 | 1.7 | 1.9375 |",
        "| **5.8** | 1.154275 | 1.1375 | 1.15 | 0.17823806 | 0.825 | 0.9875 | 1.3375 | 1.5375 |",
        "| **5.9** | 0.883825 | 0.875 | 0.9125 | 0.14808671 | 0.6 | 0.7375 | 1.0375 | 1.1875 |",
        "| **6.0** | 0.69995 | 0.7 | 0.7 | 0.12711671 | 0.475 | 0.575 | 0.825 | 0.9625 |",
        "| **6.1** | 0.537725 | 0.5375 | 0.55 | 0.10681372 | 0.3375 | 0.4375 | 0.65 | 0.75 |",
        "| **6.2** | 0.4205125 | 0.4125 | 0.4125 | 0.09030704 | 0.25 | 0.325 | 0.5125 | 0.6 |",
        "| **6.3** | 0.3265125 | 0.325 | 0.325 | 0.07760971 | 0.1875 | 0.25 | 0.4 | 0.4875 |",
        "| **6.4** | 0.2492375 | 0.25 | 0.2375 | 0.06534836 | 0.1375 | 0.175 | 0.3125 | 0.3875 |",
        "| **6.5** | 0.1891875 | 0.1875 | 0.2125 | 0.05577113 | 0.0875 | 0.1375 | 0.2375 | 0.3 |",
        "| **6.6** | 0.1438875 | 0.1375 | 0.1125 | 0.046900753 | 0.0625 | 0.1 | 0.1875 | 0.25 |",
        "| **6.7** | 0.10615 | 0.1 | 0.0875 | 0.040335212 | 0.0375 | 0.0625 | 0.15 | 0.1875 |",
        "| **6.8** | 0.080025 | 0.075 | 0.0625 | 0.034287207 | 0.025 | 0.05 | 0.1125 | 0.15 |",
        "| **6.9** | 0.059325 | 0.0625 | 0.05 | 0.028752105 | 0.0125 | 0.025 | 0.0875 | 0.125 |",
        "| **7.0** | 0.04365 | 0.0375 | 0.0375 | 0.023853647 | 0.0 | 0.025 | 0.0625 | 0.0875 |",
        "| **7.1** | 0.032 | 0.025 | 0.025 | 0.02044457 | 0.0 | 0.0125 | 0.05 | 0.075 |",
        "| **7.2** | 0.0221375 | 0.025 | 0.0125 | 0.01628965 | 0.0 | 0.0 | 0.0375 | 0.0625 |",
        "| **7.3** | 0.016725 | 0.0125 | 0.0125 | 0.014003409 | 0.0 | 0.0 | 0.025 | 0.05 |",
        "| **7.4** | 0.010825 | 0.0125 | 0.0 | 0.0113940425 | 0.0 | 0.0 | 0.025 | 0.0375 |",
        "| **7.5** | 0.0068875 | 0.0 | 0.0 | 0.009219061 | 0.0 | 0.0 | 0.0125 | 0.025 |",
        "| **7.6** | 0.003725 | 0.0 | 0.0 | 0.0068863486 | 0.0 | 0.0 | 0.0125 | 0.025 |",
        "| **7.7** | 0.0018375 | 0.0 | 0.0 | 0.004801343 | 0.0 | 0.0 | 0.0 | 0.0125 |",
        "| **7.8** | 8.5E-4 | 0.0 | 0.0 | 0.003294063 | 0.0 | 0.0 | 0.0 | 0.0125 |",
        "| **7.9** | 4.0E-4 | 0.0 | 0.0 | 0.0022011008 | 0.0 | 0.0 | 0.0 | 0.0125 |",
        "| **8.0** | 1.875E-4 | 0.0 | 0.0 | 0.0015201659 | 0.0 | 0.0 | 0.0 | 0.0 |",
        "| **8.1** | 5.0E-5 | 0.0 | 0.0 | 7.893815E-4 | 0.0 | 0.0 | 0.0 | 0.0 |",
        "| **8.2** | 0.0 | 0.0 | 0.0 | 0.0 | 0.0 | 0.0 | 0.0 | 0.0 |",
        "| **8.3** | 0.0 | 0.0 | 0.0 | 0.0 | 0.0 | 0.0 | 0.0 | 0.0 |",
        "| **8.4** | 0.0 | 0.0 | 0.0 | 0.0 | 0.0 | 0.0 | 0.0 | 0.0 |",
        "| **8.5** | 0.0 | 0.0 | 0.0 | 0.0 | 0.0 | 0.0 | 0.0 | 0.0 |",
        "| **8.6** | 0.0 | 0.0 | 0.0 | 0.0 | 0.0 | 0.0 | 0.0 | 0.0 |",
        "| **8.7** | 0.0 | 0.0 | 0.0 | 0.0 | 0.0 | 0.0 | 0.0 | 0.0 |",
        "| **8.8** | 0.0 | 0.0 | 0.0 | 0.0 | 0.0 | 0.0 | 0.0 | 0.0 |",
        "| **8.9** | 0.0 | 0.0 | 0.0 | 0.0 | 0.0 | 0.0 | 0.0 | 0.0 |",
        "| **9.0** | 0.0 | 0.0 | 0.0 | 0.0 | 0.0 | 0.0 | 0.0 | 0.0 |",
        "",
        "### 28 Year Variability",
        "*[(top)](#table-of-contents)*",
        "",
        "![Fixed Time Plot](plots/long_term_var_28yr.png)",
        "",
        "[Download CSV Here](plots/long_term_var_28yr.csv)",
        "",
        "| **Magnitude** | Mean | Median | Mode | Std. Dev. | 2.5 %-ile | 16 %-ile | 84 %-ile | 97.5 %-ile |",
        "|-----|-----|-----|-----|-----|-----|-----|-----|-----|",
        "| **5.0** | 7.845857 | 7.642857 | 7.285714 | 1.4237111 | 5.678571 | 6.535714 | 9.142858 | 11.107142 |",
        "| **5.1** | 6.209429 | 6.035714 | 5.857143 | 1.1630846 | 4.428571 | 5.142857 | 7.285714 | 8.821428 |",
        "| **5.2** | 4.911119 | 4.785714 | 4.464286 | 0.9530879 | 3.392857 | 4.035714 | 5.785714 | 7.071429 |",
        "| **5.3** | 3.873619 | 3.75 | 3.5 | 0.785968 | 2.607143 | 3.142857 | 4.607143 | 5.642857 |",
        "| **5.4** | 3.0605476 | 3.0 | 2.642857 | 0.64614266 | 2.0 | 2.4642856 | 3.6785715 | 4.5 |",
        "| **5.5** | 2.410012 | 2.357143 | 2.4642856 | 0.53083485 | 1.5 | 1.8928572 | 2.9285715 | 3.607143 |",
        "| **5.6** | 1.89375 | 1.8571428 | 1.8571428 | 0.4379711 | 1.1428572 | 1.4642857 | 2.3214285 | 2.857143 |",
        "| **5.7** | 1.479 | 1.4285715 | 1.5357143 | 0.3660112 | 0.85714287 | 1.1428572 | 1.8214285 | 2.2857144 |",
        "| **5.8** | 1.1527381 | 1.1071428 | 1.0 | 0.30227312 | 0.64285713 | 0.85714287 | 1.4642857 | 1.8214285 |",
        "| **5.9** | 0.88245237 | 0.85714287 | 0.78571427 | 0.2511054 | 0.4642857 | 0.64285713 | 1.1071428 | 1.4285715 |",
        "| **6.0** | 0.6985 | 0.6785714 | 0.64285713 | 0.21448599 | 0.32142857 | 0.5 | 0.89285713 | 1.1785715 |",
        "| **6.1** | 0.53667855 | 0.53571427 | 0.53571427 | 0.1802024 | 0.21428572 | 0.35714287 | 0.71428573 | 0.9285714 |",
        "| **6.2** | 0.41989285 | 0.39285713 | 0.35714287 | 0.15271653 | 0.14285715 | 0.2857143 | 0.5714286 | 0.75 |",
        "| **6.3** | 0.3257738 | 0.32142857 | 0.2857143 | 0.12873597 | 0.10714286 | 0.21428572 | 0.4642857 | 0.60714287 |",
        "| **6.4** | 0.24855952 | 0.25 | 0.25 | 0.10887374 | 0.071428575 | 0.14285715 | 0.35714287 | 0.5 |",
        "| **6.5** | 0.18864286 | 0.17857143 | 0.14285715 | 0.093127415 | 0.035714287 | 0.10714286 | 0.2857143 | 0.39285713 |",
        "| **6.6** | 0.14336905 | 0.14285715 | 0.10714286 | 0.07929138 | 0.0 | 0.071428575 | 0.21428572 | 0.32142857 |",
        "| **6.7** | 0.105845235 | 0.10714286 | 0.071428575 | 0.06665132 | 0.0 | 0.035714287 | 0.17857143 | 0.25 |",
        "| **6.8** | 0.079738095 | 0.071428575 | 0.035714287 | 0.056522314 | 0.0 | 0.035714287 | 0.14285715 | 0.21428572 |",
        "| **6.9** | 0.059190474 | 0.035714287 | 0.035714287 | 0.047949187 | 0.0 | 0.0 | 0.10714286 | 0.17857143 |",
        "| **7.0** | 0.04372619 | 0.035714287 | 0.035714287 | 0.040570516 | 0.0 | 0.0 | 0.071428575 | 0.14285715 |",
        "| **7.1** | 0.032035716 | 0.035714287 | 0.0 | 0.034503933 | 0.0 | 0.0 | 0.071428575 | 0.10714286 |",
        "| **7.2** | 0.022154761 | 0.0 | 0.0 | 0.028115252 | 0.0 | 0.0 | 0.035714287 | 0.071428575 |",
        "| **7.3** | 0.016738094 | 0.0 | 0.0 | 0.024253443 | 0.0 | 0.0 | 0.035714287 | 0.071428575 |",
        "| **7.4** | 0.010964286 | 0.0 | 0.0 | 0.019783692 | 0.0 | 0.0 | 0.035714287 | 0.071428575 |",
        "| **7.5** | 0.007047619 | 0.0 | 0.0 | 0.015936974 | 0.0 | 0.0 | 0.035714287 | 0.035714287 |",
        "| **7.6** | 0.0038333333 | 0.0 | 0.0 | 0.011619398 | 0.0 | 0.0 | 0.0 | 0.035714287 |",
        "| **7.7** | 0.0018809524 | 0.0 | 0.0 | 0.008189176 | 0.0 | 0.0 | 0.0 | 0.035714287 |",
        "| **7.8** | 8.809524E-4 | 0.0 | 0.0 | 0.005616704 | 0.0 | 0.0 | 0.0 | 0.0 |",
        "| **7.9** | 4.2857142E-4 | 0.0 | 0.0 | 0.0038894075 | 0.0 | 0.0 | 0.0 | 0.0 |",
        "| **8.0** | 2.0238095E-4 | 0.0 | 0.0 | 0.0026812926 | 0.0 | 0.0 | 0.0 | 0.0 |",
        "| **8.1** | 5.952381E-5 | 0.0 | 0.0 | 0.001457057 | 0.0 | 0.0 | 0.0 | 0.0 |",
        "| **8.2** | 0.0 | 0.0 | 0.0 | 0.0 | 0.0 | 0.0 | 0.0 | 0.0 |",
        "| **8.3** | 0.0 | 0.0 | 0.0 | 0.0 | 0.0 | 0.0 | 0.0 | 0.0 |",
        "| **8.4** | 0.0 | 0.0 | 0.0 | 0.0 | 0.0 | 0.0 | 0.0 | 0.0 |",
        "| **8.5** | 0.0 | 0.0 | 0.0 | 0.0 | 0.0 | 0.0 | 0.0 | 0.0 |",
        "| **8.6** | 0.0 | 0.0 | 0.0 | 0.0 | 0.0 | 0.0 | 0.0 | 0.0 |",
        "| **8.7** | 0.0 | 0.0 | 0.0 | 0.0 | 0.0 | 0.0 | 0.0 | 0.0 |",
        "| **8.8** | 0.0 | 0.0 | 0.0 | 0.0 | 0.0 | 0.0 | 0.0 | 0.0 |",
        "| **8.9** | 0.0 | 0.0 | 0.0 | 0.0 | 0.0 | 0.0 | 0.0 | 0.0 |",
        "| **9.0** | 0.0 | 0.0 | 0.0 | 0.0 | 0.0 | 0.0 | 0.0 | 0.0 |",
        "",
        "### Variability Duration Dependence",
        "*[(top)](#table-of-contents)*",
        "",
        "![Duration Dependence Plot](plots/long_term_var_m5.png)",
        "",
        "[Download CSV Here](plots/long_term_var_m5.csv)",
        "",
        "| **Duration (years)** | Mean | Median | Mode | Std. Dev. | 2.5 %-ile | 16 %-ile | 84 %-ile | 97.5 %-ile |",
        "|-----|-----|-----|-----|-----|-----|-----|-----|-----|",
        "| **1.0** | 7.84163 | 7.0 | 5.0 | 6.088256 | 1.0 | 4.0 | 11.0 | 22.0 |",
        "| **2.0** | 7.84163 | 7.0 | 6.5 | 4.5498853 | 2.5 | 4.5 | 10.5 | 19.0 |",
        "| **4.0** | 7.84163 | 7.25 | 6.5 | 3.3927145 | 3.5 | 5.25 | 10.25 | 16.25 |",
        "| **6.0** | 7.838281 | 7.3333335 | 7.0 | 2.8481467 | 4.1666665 | 5.5 | 10.0 | 14.833333 |",
        "| **8.0** | 7.838281 | 7.375 | 7.125 | 2.5152593 | 4.5 | 5.75 | 9.75 | 14.125 |",
        "| **10.0** | 7.84163 | 7.4 | 7.1 | 2.3022428 | 4.7 | 5.9 | 9.7 | 13.8 |",
        "| **12.0** | 7.838281 | 7.4166665 | 7.0833335 | 2.1194367 | 4.9166665 | 6.0 | 9.666667 | 13.083333 |",
        "| **14.0** | 7.8405104 | 7.5 | 7.571429 | 1.9859697 | 5.071429 | 6.071429 | 9.5 | 12.928572 |",
        "| **16.0** | 7.838281 | 7.5 | 7.125 | 1.8761245 | 5.125 | 6.1875 | 9.4375 | 12.4375 |",
        "| **18.0** | 7.841089 | 7.5555553 | 7.2777777 | 1.7593253 | 5.2222223 | 6.2777777 | 9.388889 | 12.166667 |",
        "| **20.0** | 7.84163 | 7.55 | 6.85 | 1.7277759 | 5.35 | 6.3 | 9.35 | 12.05 |",
        "| **22.0** | 7.8387275 | 7.590909 | 7.1363635 | 1.608676 | 5.409091 | 6.3636365 | 9.272727 | 11.590909 |",
        "| **24.0** | 7.838281 | 7.5833335 | 7.25 | 1.5610905 | 5.4583335 | 6.4166665 | 9.208333 | 11.708333 |",
        "| **26.0** | 7.862923 | 7.6923075 | 7.576923 | 1.4673731 | 5.5384617 | 6.5384617 | 9.153846 | 11.384615 |",
        "| **28.0** | 7.845857 | 7.642857 | 7.285714 | 1.4237111 | 5.678571 | 6.535714 | 9.142858 | 11.107142 |",
        "| **30.0** | 7.841089 | 7.6 | 7.2 | 1.3960496 | 5.7 | 6.5666666 | 9.1 | 11.166667 |",
        "| **32.0** | 7.838281 | 7.625 | 7.25 | 1.3614373 | 5.75 | 6.59375 | 9.09375 | 11.15625 |",
        "| **34.0** | 7.879456 | 7.7058825 | 7.5588236 | 1.2784562 | 5.852941 | 6.6764708 | 9.117647 | 10.882353 |",
        "| **36.0** | 7.869694 | 7.6944447 | 7.5277777 | 1.2621498 | 5.861111 | 6.638889 | 9.055555 | 10.805555 |",
        "| **38.0** | 7.8671713 | 7.7105265 | 7.5526314 | 1.2290792 | 5.868421 | 6.6842103 | 9.052631 | 10.763158 |",
        "| **40.0** | 7.8577623 | 7.7 | 7.5 | 1.2085657 | 5.9 | 6.675 | 9.025 | 10.675 |",
        "| **42.0** | 7.845857 | 7.6904764 | 8.0 | 1.1906183 | 5.904762 | 6.714286 | 8.976191 | 10.619047 |",
        "| **44.0** | 7.8387275 | 7.7272725 | 7.75 | 1.1682348 | 5.9545455 | 6.7045455 | 8.931818 | 10.545455 |",
        "| **46.0** | 7.841598 | 7.7173915 | 7.347826 | 1.1514541 | 5.978261 | 6.7391305 | 8.934783 | 10.565217 |",
        "| **48.0** | 7.838281 | 7.7083335 | 7.7291665 | 1.1356798 | 5.9583335 | 6.7708335 | 8.916667 | 10.604167 |",
        "| **50.0** | 7.84163 | 7.68 | 7.56 | 1.1244092 | 5.98 | 6.76 | 8.9 | 10.5 |",
        "| **52.0** | 7.9149423 | 7.8076925 | 8.153846 | 1.0480798 | 6.1923075 | 6.8653846 | 8.884615 | 10.288462 |",
        "| **54.0** | 7.903111 | 7.796296 | 7.611111 | 1.0298122 | 6.203704 | 6.8703704 | 8.888889 | 10.314815 |",
        "| **56.0** | 7.8950176 | 7.785714 | 7.589286 | 1.0087471 | 6.232143 | 6.892857 | 8.875 | 10.196428 |",
        "| **58.0** | 7.889241 | 7.775862 | 8.0 | 0.99631625 | 6.2413793 | 6.913793 | 8.844828 | 10.172414 |",
        "| **60.0** | 7.8812666 | 7.766667 | 7.766667 | 0.98596233 | 6.2166667 | 6.9333334 | 8.816667 | 10.166667 |",
        "| **62.0** | 7.8851614 | 7.806452 | 7.5 | 0.9712356 | 6.2419353 | 6.935484 | 8.83871 | 10.064516 |",
        "| **64.0** | 7.8868437 | 7.796875 | 7.75 | 0.9528132 | 6.234375 | 6.9375 | 8.796875 | 10.03125 |",
        "| **66.0** | 7.882773 | 7.8030305 | 8.166667 | 0.94143456 | 6.257576 | 6.9242425 | 8.80303 | 9.939394 |",
        "| **68.0** | 7.879456 | 7.7941175 | 7.75 | 0.9325941 | 6.279412 | 6.9411764 | 8.779411 | 9.955882 |",
        "| **70.0** | 7.8706713 | 7.785714 | 8.3 | 0.9221721 | 6.2714286 | 6.9428573 | 8.757143 | 9.914286 |",
        "| **72.0** | 7.869694 | 7.7777777 | 7.638889 | 0.90968066 | 6.2916665 | 6.9583335 | 8.777778 | 9.916667 |",
        "| **74.0** | 7.868054 | 7.7972975 | 7.716216 | 0.90083176 | 6.3378377 | 6.972973 | 8.743243 | 9.878378 |",
        "| **76.0** | 7.8671713 | 7.7894735 | 7.7894735 | 0.89433074 | 6.3421054 | 6.9736843 | 8.723684 | 9.934211 |",
        "| **78.0** | 7.862923 | 7.769231 | 7.6666665 | 0.8879319 | 6.3717947 | 6.9871793 | 8.730769 | 9.98718 |",
        "| **80.0** | 7.8577623 | 7.7625 | 7.825 | 0.87604946 | 6.375 | 7.0125 | 8.725 | 9.925 |",
        "| **82.0** | 7.8522196 | 7.756098 | 7.5609756 | 0.86087483 | 6.390244 | 7.02439 | 8.695122 | 9.841463 |",
        "| **84.0** | 7.845857 | 7.75 | 7.6309524 | 0.855268 | 6.392857 | 7.0238094 | 8.678572 | 9.833333 |",
        "| **86.0** | 7.8423605 | 7.744186 | 7.1511626 | 0.8454726 | 6.4069767 | 7.023256 | 8.697675 | 9.790698 |",
        "| **88.0** | 7.8387275 | 7.7386365 | 7.6477275 | 0.8422505 | 6.431818 | 7.0227275 | 8.681818 | 9.829545 |",
        "| **90.0** | 7.841089 | 7.7555556 | 7.766667 | 0.83365387 | 6.477778 | 7.0555553 | 8.666667 | 9.811111 |",
        "| **92.0** | 7.841598 | 7.7608695 | 7.2065215 | 0.8257319 | 6.4565215 | 7.0652175 | 8.673913 | 9.771739 |",
        "| **94.0** | 7.842872 | 7.744681 | 7.62766 | 0.8218834 | 6.4787235 | 7.06383 | 8.648936 | 9.712766 |",
        "| **96.0** | 7.838281 | 7.75 | 7.9479165 | 0.81520647 | 6.46875 | 7.0416665 | 8.635417 | 9.697917 |",
        "| **98.0** | 7.8405104 | 7.765306 | 8.051021 | 0.80952156 | 6.4489794 | 7.0510206 | 8.622449 | 9.632653 |",
        "| **100.0** | 7.84163 | 7.78 | 7.55 | 0.8000935 | 6.49 | 7.04 | 8.64 | 9.66 |",
        ""
      ]
    },
    {
      "className": "scratch.UCERF3.erf.ETAS.analysis.ETAS_StationarityPlot",
      "version": 1,
      "time": 1567403276738,
      "markdown": [
        "## Simulation Stationarity",
        "*[(top)](#table-of-contents)*",
        "",
        "![Stationarity Plot](plots/stationarity.png)",
        ""
      ]
    },
    {
      "className": "scratch.UCERF3.erf.ETAS.analysis.ETAS_FaultParticipationPlot",
      "version": 1,
      "time": 1567403276738,
      "markdown": [
        "## Section Participation",
        "*[(top)](#table-of-contents)*",
        "",
        "### Section Participation Plots",
        "*[(top)](#table-of-contents)*",
        "",
        "| Min Mag | Complete Catalog (including spontaneous) |",
        "|-----|-----|",
        "| **All Supra. Seis.** | ![Participation Plot](plots/fault_participation_partic.png) |",
        "| **M\u0026ge;6.5** | ![Participation Plot](plots/fault_participation_partic_m6.5.png) |",
        "| **M\u0026ge;7** | ![Participation Plot](plots/fault_participation_partic_m7.0.png) |",
        "| **M\u0026ge;7.5** | ![Participation Plot](plots/fault_participation_partic_m7.5.png) |",
        "| **M\u0026ge;8** | ![Participation Plot](plots/fault_participation_partic_m8.0.png) |",
        "",
        "### Supra-Seismogenic Parent Sections Table",
        "*[(top)](#table-of-contents)*",
        "",
        "*First 10 of 313 with matching ruptures shown*",
        "",
        "| Parent Name | Total Mean Annual Rate | Total 100 Year Prob |",
        "|-----|-----|-----|",
        "| San Andreas (Parkfield) | 0.04375 | 0.998 |",
        "| San Andreas (Creeping Section) 2011 CFM | 0.0259 | 0.963 |",
        "| San Andreas (Mojave S) | 0.01669 | 0.845 |",
        "| Mendocino | 0.01521 | 0.826 |",
        "| Cerro Prieto | 0.01209 | 0.798 |",
        "| Imperial | 0.01179 | 0.798 |",
        "| Brawley (Seismic Zone) alt 1 | 0.01085 | 0.766 |",
        "| Hayward (So) 2011 CFM | 0.00618 | 0.516 |",
        "| Hunting Creek - Berryessa 2011 CFM | 0.00613 | 0.48 |",
        "| San Andreas (Coachella) rev | 0.00611 | 0.551 |",
        "",
        "### M≥6.5 Parent Sections Table",
        "*[(top)](#table-of-contents)*",
        "",
        "*First 10 of 302 with matching ruptures shown*",
        "",
        "| Parent Name | Total Mean Annual Rate | Total 100 Year Prob |",
        "|-----|-----|-----|",
        "| Cerro Prieto | 0.01015 | 0.732 |",
        "| Imperial | 0.0082 | 0.641 |",
        "| Brawley (Seismic Zone) alt 1 | 0.00775 | 0.623 |",
        "| San Andreas (Creeping Section) 2011 CFM | 0.00637 | 0.5 |",
        "| Mendocino | 0.00592 | 0.493 |",
        "| San Andreas (Coachella) rev | 0.00523 | 0.488 |",
        "| Hayward (So) 2011 CFM | 0.00506 | 0.446 |",
        "| San Andreas (San Bernardino N) | 0.00389 | 0.357 |",
        "| San Andreas (Mojave S) | 0.00368 | 0.342 |",
        "| San Andreas (San Bernardino S) | 0.00363 | 0.343 |",
        "",
        "### M≥7 Parent Sections Table",
        "*[(top)](#table-of-contents)*",
        "",
        "*First 10 of 261 with matching ruptures shown*",
        "",
        "| Parent Name | Total Mean Annual Rate | Total 100 Year Prob |",
        "|-----|-----|-----|",
        "| San Andreas (Coachella) rev | 0.0043 | 0.418 |",
        "| Brawley (Seismic Zone) alt 1 | 0.00407 | 0.398 |",
        "| Imperial | 0.00398 | 0.389 |",
        "| Cerro Prieto | 0.00331 | 0.317 |",
        "| San Andreas (San Gorgonio Pass-Garnet HIll) | 0.00331 | 0.323 |",
        "| San Andreas (Cholame) rev | 0.0022 | 0.217 |",
        "| San Andreas (Carrizo) rev | 0.00205 | 0.202 |",
        "| San Andreas (Creeping Section) 2011 CFM | 0.00202 | 0.194 |",
        "| San Andreas (San Bernardino S) | 0.00191 | 0.189 |",
        "| Maacama 2011 CFM | 0.00189 | 0.185 |",
        "",
        "### M≥7.5 Parent Sections Table",
        "*[(top)](#table-of-contents)*",
        "",
        "*First 10 of 180 with matching ruptures shown*",
        "",
        "| Parent Name | Total Mean Annual Rate | Total 100 Year Prob |",
        "|-----|-----|-----|",
        "| San Andreas (Coachella) rev | 0.00137 | 0.137 |",
        "| San Andreas (San Gorgonio Pass-Garnet HIll) | 0.00137 | 0.136 |",
        "| Brawley (Seismic Zone) alt 1 | 0.00127 | 0.127 |",
        "| San Andreas (San Bernardino S) | 0.00126 | 0.126 |",
        "| Imperial | 0.0012 | 0.12 |",
        "| San Andreas (Mojave N) | 0.0011 | 0.109 |",
        "| San Andreas (Mojave S) | 0.00103 | 0.102 |",
        "| San Andreas (Big Bend) | 0.00101 | 0.099 |",
        "| San Andreas (Carrizo) rev | 9.9E-4 | 0.098 |",
        "| San Andreas (San Bernardino N) | 9.8E-4 | 0.097 |",
        "",
        "### M≥8 Parent Sections Table",
        "*[(top)](#table-of-contents)*",
        "",
        "*First 10 of 31 with matching ruptures shown*",
        "",
        "| Parent Name | Total Mean Annual Rate | Total 100 Year Prob |",
        "|-----|-----|-----|",
        "| San Andreas (Big Bend) | 3.3E-4 | 0.033 |",
        "| San Andreas (Carrizo) rev | 3.3E-4 | 0.033 |",
        "| San Andreas (Mojave N) | 3.3E-4 | 0.033 |",
        "| San Andreas (Mojave S) | 3.3E-4 | 0.033 |",
        "| San Andreas (San Bernardino N) | 3.3E-4 | 0.033 |",
        "| San Andreas (Cholame) rev | 3.2E-4 | 0.032 |",
        "| San Andreas (Parkfield) | 2.9E-4 | 0.029 |",
        "| San Andreas (Creeping Section) 2011 CFM | 2.5E-4 | 0.025 |",
        "| San Andreas (San Bernardino S) | 1.7E-4 | 0.017 |",
        "| San Andreas (San Gorgonio Pass-Garnet HIll) | 1.7E-4 | 0.017 |"
      ]
    },
    {
      "className": "scratch.UCERF3.erf.ETAS.analysis.ETAS_GriddedNucleationPlot",
      "version": 1,
      "time": 1567403276738,
      "markdown": [
        "## Gridded Nucleation",
        "*[(top)](#table-of-contents)*",
        "",
        "| Min Mag | Complete Catalog (including spontaneous) |",
        "|-----|-----|",
        "| **M\u0026ge;5** | ![Nucleation Plot](plots/gridded_nucleation_m5.0.png) |",
        "| **M\u0026ge;6** | ![Nucleation Plot](plots/gridded_nucleation_m6.0.png) |",
        "| **M\u0026ge;7** | ![Nucleation Plot](plots/gridded_nucleation_m7.0.png) |"
      ]
    }
  ]
}
